<?xml version="1.0" encoding="UTF-8"?>
<!-- Created by BioNetGen 2.6.0  -->
<sbml xmlns="http://www.sbml.org/sbml/level3" level="3" version="1">
  <model id="bmd0000000539_atomized">
    <ListOfParameters>
      <Parameter id="theta" type="Constant" value="0.04" expr="0.04"/>
      <Parameter id="alpha" type="Constant" value="0.001" expr="0.001"/>
      <Parameter id="rhob" type="Constant" value="5" expr="5.0"/>
      <Parameter id="rhof" type="Constant" value="0.1" expr="0.1"/>
      <Parameter id="deltar" type="Constant" value="0.03" expr="0.03"/>
      <Parameter id="rhoA" type="Constant" value="100" expr="100.0"/>
      <Parameter id="gamma" type="Constant" value="1" expr="1.0"/>
      <Parameter id="deltaA" type="Constant" value="0.01" expr="0.01"/>
      <Parameter id="deltaB" type="Constant" value="0.01" expr="0.01"/>
      <Parameter id="beta" type="Constant" value="3" expr="3.0"/>
      <Parameter id="deltaAB" type="Constant" value="0.01" expr="0.01"/>
    </ListOfParameters>
    <ListOfMoleculeTypes>
      <MoleculeType id="A">
        <ListOfComponentTypes>
          <ComponentType id="b"/>
          <ComponentType id="gb"/>
        </ListOfComponentTypes>
      </MoleculeType>
      <MoleculeType id="B">
        <ListOfComponentTypes>
          <ComponentType id="a"/>
        </ListOfComponentTypes>
      </MoleculeType>
      <MoleculeType id="gB">
        <ListOfComponentTypes>
          <ComponentType id="a"/>
        </ListOfComponentTypes>
      </MoleculeType>
      <MoleculeType id="rB"/>
    </ListOfMoleculeTypes>
    <ListOfCompartments>
    </ListOfCompartments>
    <ListOfSpecies>
      <Species id="S1"  concentration="2.4088e+25" name="A(b,gb)">
        <ListOfMolecules>
          <Molecule id="S1_M1" name="A">
            <ListOfComponents>
              <Component id="S1_M1_C1" name="b" numberOfBonds="0"/>
              <Component id="S1_M1_C2" name="gb" numberOfBonds="0"/>
            </ListOfComponents>
          </Molecule>
        </ListOfMolecules>
      </Species>
      <Species id="S2"  concentration="6.022e+23" name="gB(a)">
        <ListOfMolecules>
          <Molecule id="S2_M1" name="gB">
            <ListOfComponents>
              <Component id="S2_M1_C1" name="a" numberOfBonds="0"/>
            </ListOfComponents>
          </Molecule>
        </ListOfMolecules>
      </Species>
    </ListOfSpecies>
    <ListOfReactionRules>
      <ReactionRule id="RR1" name="A_binds_gB" symmetry_factor="1">
        <ListOfReactantPatterns>
          <ReactantPattern id="RR1_RP1">
            <ListOfMolecules>
              <Molecule id="RR1_RP1_M1" name="A">
                <ListOfComponents>
                  <Component id="RR1_RP1_M1_C1" name="b" numberOfBonds="0"/>
                  <Component id="RR1_RP1_M1_C2" name="gb" numberOfBonds="0"/>
                </ListOfComponents>
              </Molecule>
            </ListOfMolecules>
          </ReactantPattern>
          <ReactantPattern id="RR1_RP2">
            <ListOfMolecules>
              <Molecule id="RR1_RP2_M1" name="gB">
                <ListOfComponents>
                  <Component id="RR1_RP2_M1_C1" name="a" numberOfBonds="0"/>
                </ListOfComponents>
              </Molecule>
            </ListOfMolecules>
          </ReactantPattern>
        </ListOfReactantPatterns>
        <ListOfProductPatterns>
          <ProductPattern id="RR1_PP1">
            <ListOfMolecules>
              <Molecule id="RR1_PP1_M1" name="A">
                <ListOfComponents>
                  <Component id="RR1_PP1_M1_C1" name="b" numberOfBonds="0"/>
                  <Component id="RR1_PP1_M1_C2" name="gb" numberOfBonds="1"/>
                </ListOfComponents>
              </Molecule>
              <Molecule id="RR1_PP1_M2" name="gB">
                <ListOfComponents>
                  <Component id="RR1_PP1_M2_C1" name="a" numberOfBonds="1"/>
                </ListOfComponents>
              </Molecule>
            </ListOfMolecules>
            <ListOfBonds>
              <Bond id="RR1_PP1_B1" site1="RR1_PP1_M1_C2" site2="RR1_PP1_M2_C1"/>
            </ListOfBonds>
          </ProductPattern>
        </ListOfProductPatterns>
        <RateLaw id="RR1_RateLaw" type="Ele" totalrate="0">
          <ListOfRateConstants>
            <RateConstant value="alpha"/>
          </ListOfRateConstants>
        </RateLaw>
        <Map>
          <MapItem sourceID="RR1_RP1_M1" targetID="RR1_PP1_M1"/>
          <MapItem sourceID="RR1_RP1_M1_C1" targetID="RR1_PP1_M1_C1"/>
          <MapItem sourceID="RR1_RP1_M1_C2" targetID="RR1_PP1_M1_C2"/>
          <MapItem sourceID="RR1_RP2_M1" targetID="RR1_PP1_M2"/>
          <MapItem sourceID="RR1_RP2_M1_C1" targetID="RR1_PP1_M2_C1"/>
        </Map>
        <ListOfOperations>
          <AddBond site1="RR1_RP1_M1_C2" site2="RR1_RP2_M1_C1"/>
        </ListOfOperations>
      </ReactionRule>
      <ReactionRule id="RR2" name="gB_releases_A" symmetry_factor="1">
        <ListOfReactantPatterns>
          <ReactantPattern id="RR2_RP1">
            <ListOfMolecules>
              <Molecule id="RR2_RP1_M1" name="A">
                <ListOfComponents>
                  <Component id="RR2_RP1_M1_C1" name="b" numberOfBonds="0"/>
                  <Component id="RR2_RP1_M1_C2" name="gb" numberOfBonds="1"/>
                </ListOfComponents>
              </Molecule>
              <Molecule id="RR2_RP1_M2" name="gB">
                <ListOfComponents>
                  <Component id="RR2_RP1_M2_C1" name="a" numberOfBonds="1"/>
                </ListOfComponents>
              </Molecule>
            </ListOfMolecules>
            <ListOfBonds>
              <Bond id="RR2_RP1_B1" site1="RR2_RP1_M1_C2" site2="RR2_RP1_M2_C1"/>
            </ListOfBonds>
          </ReactantPattern>
        </ListOfReactantPatterns>
        <ListOfProductPatterns>
          <ProductPattern id="RR2_PP1">
            <ListOfMolecules>
              <Molecule id="RR2_PP1_M1" name="A">
                <ListOfComponents>
                  <Component id="RR2_PP1_M1_C1" name="b" numberOfBonds="0"/>
                  <Component id="RR2_PP1_M1_C2" name="gb" numberOfBonds="0"/>
                </ListOfComponents>
              </Molecule>
            </ListOfMolecules>
          </ProductPattern>
          <ProductPattern id="RR2_PP2">
            <ListOfMolecules>
              <Molecule id="RR2_PP2_M1" name="gB">
                <ListOfComponents>
                  <Component id="RR2_PP2_M1_C1" name="a" numberOfBonds="0"/>
                </ListOfComponents>
              </Molecule>
            </ListOfMolecules>
          </ProductPattern>
        </ListOfProductPatterns>
        <RateLaw id="RR2_RateLaw" type="Ele" totalrate="0">
          <ListOfRateConstants>
            <RateConstant value="theta"/>
          </ListOfRateConstants>
        </RateLaw>
        <Map>
          <MapItem sourceID="RR2_RP1_M1" targetID="RR2_PP1_M1"/>
          <MapItem sourceID="RR2_RP1_M1_C1" targetID="RR2_PP1_M1_C1"/>
          <MapItem sourceID="RR2_RP1_M1_C2" targetID="RR2_PP1_M1_C2"/>
          <MapItem sourceID="RR2_RP1_M2" targetID="RR2_PP2_M1"/>
          <MapItem sourceID="RR2_RP1_M2_C1" targetID="RR2_PP2_M1_C1"/>
        </Map>
        <ListOfOperations>
          <DeleteBond site1="RR2_RP1_M1_C2" site2="RR2_RP1_M2_C1"/>
        </ListOfOperations>
      </ReactionRule>
      <ReactionRule id="RR3" name="basal_transcription_B" symmetry_factor="1">
        <ListOfReactantPatterns>
        </ListOfReactantPatterns>
        <ListOfProductPatterns>
          <ProductPattern id="RR3_PP1">
            <ListOfMolecules>
              <Molecule id="RR3_PP1_M1" name="rB"/>
            </ListOfMolecules>
          </ProductPattern>
        </ListOfProductPatterns>
        <RateLaw id="RR3_RateLaw" type="Function" name="fRate2" totalrate="0">
          <ListOfArguments>
          </ListOfArguments>
        </RateLaw>
        <Map>
        </Map>
        <ListOfOperations>
          <Add id="RR3_PP1_M1"/>
        </ListOfOperations>
      </ReactionRule>
      <ReactionRule id="RR4" name="stim_transcription_B" symmetry_factor="1">
        <ListOfReactantPatterns>
        </ListOfReactantPatterns>
        <ListOfProductPatterns>
          <ProductPattern id="RR4_PP1">
            <ListOfMolecules>
              <Molecule id="RR4_PP1_M1" name="rB"/>
            </ListOfMolecules>
          </ProductPattern>
        </ListOfProductPatterns>
        <RateLaw id="RR4_RateLaw" type="Function" name="fRate3" totalrate="0">
          <ListOfArguments>
          </ListOfArguments>
        </RateLaw>
        <Map>
        </Map>
        <ListOfOperations>
          <Add id="RR4_PP1_M1"/>
        </ListOfOperations>
      </ReactionRule>
      <ReactionRule id="RR5" name="degradation_mRNA_B" symmetry_factor="1">
        <ListOfReactantPatterns>
          <ReactantPattern id="RR5_RP1">
            <ListOfMolecules>
              <Molecule id="RR5_RP1_M1" name="rB"/>
            </ListOfMolecules>
          </ReactantPattern>
        </ListOfReactantPatterns>
        <ListOfProductPatterns>
        </ListOfProductPatterns>
        <RateLaw id="RR5_RateLaw" type="Ele" totalrate="0">
          <ListOfRateConstants>
            <RateConstant value="deltar"/>
          </ListOfRateConstants>
        </RateLaw>
        <Map>
          <MapItem sourceID="RR5_RP1_M1"/>
        </Map>
        <ListOfOperations>
          <Delete id="RR5_RP1" DeleteMolecules="0"/>
        </ListOfOperations>
      </ReactionRule>
      <ReactionRule id="RR6" name="production_A" symmetry_factor="1">
        <ListOfReactantPatterns>
        </ListOfReactantPatterns>
        <ListOfProductPatterns>
          <ProductPattern id="RR6_PP1">
            <ListOfMolecules>
              <Molecule id="RR6_PP1_M1" name="A">
                <ListOfComponents>
                  <Component id="RR6_PP1_M1_C1" name="b" numberOfBonds="0"/>
                  <Component id="RR6_PP1_M1_C2" name="gb" numberOfBonds="0"/>
                </ListOfComponents>
              </Molecule>
            </ListOfMolecules>
          </ProductPattern>
        </ListOfProductPatterns>
        <RateLaw id="RR6_RateLaw" type="Ele" totalrate="0">
          <ListOfRateConstants>
            <RateConstant value="rhoA"/>
          </ListOfRateConstants>
        </RateLaw>
        <Map>
        </Map>
        <ListOfOperations>
          <Add id="RR6_PP1_M1"/>
        </ListOfOperations>
      </ReactionRule>
      <ReactionRule id="RR7" name="degradation_A" symmetry_factor="1">
        <ListOfReactantPatterns>
          <ReactantPattern id="RR7_RP1">
            <ListOfMolecules>
              <Molecule id="RR7_RP1_M1" name="A">
                <ListOfComponents>
                  <Component id="RR7_RP1_M1_C1" name="b" numberOfBonds="0"/>
                  <Component id="RR7_RP1_M1_C2" name="gb" numberOfBonds="0"/>
                </ListOfComponents>
              </Molecule>
            </ListOfMolecules>
          </ReactantPattern>
        </ListOfReactantPatterns>
        <ListOfProductPatterns>
        </ListOfProductPatterns>
        <RateLaw id="RR7_RateLaw" type="Ele" totalrate="0">
          <ListOfRateConstants>
            <RateConstant value="deltaA"/>
          </ListOfRateConstants>
        </RateLaw>
        <Map>
          <MapItem sourceID="RR7_RP1_M1"/>
          <MapItem sourceID="RR7_RP1_M1_C1"/>
          <MapItem sourceID="RR7_RP1_M1_C2"/>
        </Map>
        <ListOfOperations>
          <Delete id="RR7_RP1" DeleteMolecules="0"/>
        </ListOfOperations>
      </ReactionRule>
      <ReactionRule id="RR8" name="translation_B" symmetry_factor="1">
        <ListOfReactantPatterns>
        </ListOfReactantPatterns>
        <ListOfProductPatterns>
          <ProductPattern id="RR8_PP1">
            <ListOfMolecules>
              <Molecule id="RR8_PP1_M1" name="B">
                <ListOfComponents>
                  <Component id="RR8_PP1_M1_C1" name="a" numberOfBonds="0"/>
                </ListOfComponents>
              </Molecule>
            </ListOfMolecules>
          </ProductPattern>
        </ListOfProductPatterns>
        <RateLaw id="RR8_RateLaw" type="Function" name="fRate7" totalrate="0">
          <ListOfArguments>
          </ListOfArguments>
        </RateLaw>
        <Map>
        </Map>
        <ListOfOperations>
          <Add id="RR8_PP1_M1"/>
        </ListOfOperations>
      </ReactionRule>
      <ReactionRule id="RR9" name="degradation_B" symmetry_factor="1">
        <ListOfReactantPatterns>
          <ReactantPattern id="RR9_RP1">
            <ListOfMolecules>
              <Molecule id="RR9_RP1_M1" name="B">
                <ListOfComponents>
                  <Component id="RR9_RP1_M1_C1" name="a" numberOfBonds="0"/>
                </ListOfComponents>
              </Molecule>
            </ListOfMolecules>
          </ReactantPattern>
        </ListOfReactantPatterns>
        <ListOfProductPatterns>
        </ListOfProductPatterns>
        <RateLaw id="RR9_RateLaw" type="Ele" totalrate="0">
          <ListOfRateConstants>
            <RateConstant value="deltaB"/>
          </ListOfRateConstants>
        </RateLaw>
        <Map>
          <MapItem sourceID="RR9_RP1_M1"/>
          <MapItem sourceID="RR9_RP1_M1_C1"/>
        </Map>
        <ListOfOperations>
          <Delete id="RR9_RP1" DeleteMolecules="0"/>
        </ListOfOperations>
      </ReactionRule>
      <ReactionRule id="RR10" name="formation_dimer" symmetry_factor="1">
        <ListOfReactantPatterns>
          <ReactantPattern id="RR10_RP1">
            <ListOfMolecules>
              <Molecule id="RR10_RP1_M1" name="A">
                <ListOfComponents>
                  <Component id="RR10_RP1_M1_C1" name="b" numberOfBonds="0"/>
                  <Component id="RR10_RP1_M1_C2" name="gb" numberOfBonds="0"/>
                </ListOfComponents>
              </Molecule>
            </ListOfMolecules>
          </ReactantPattern>
          <ReactantPattern id="RR10_RP2">
            <ListOfMolecules>
              <Molecule id="RR10_RP2_M1" name="B">
                <ListOfComponents>
                  <Component id="RR10_RP2_M1_C1" name="a" numberOfBonds="0"/>
                </ListOfComponents>
              </Molecule>
            </ListOfMolecules>
          </ReactantPattern>
        </ListOfReactantPatterns>
        <ListOfProductPatterns>
          <ProductPattern id="RR10_PP1">
            <ListOfMolecules>
              <Molecule id="RR10_PP1_M1" name="A">
                <ListOfComponents>
                  <Component id="RR10_PP1_M1_C1" name="b" numberOfBonds="1"/>
                  <Component id="RR10_PP1_M1_C2" name="gb" numberOfBonds="0"/>
                </ListOfComponents>
              </Molecule>
              <Molecule id="RR10_PP1_M2" name="B">
                <ListOfComponents>
                  <Component id="RR10_PP1_M2_C1" name="a" numberOfBonds="1"/>
                </ListOfComponents>
              </Molecule>
            </ListOfMolecules>
            <ListOfBonds>
              <Bond id="RR10_PP1_B1" site1="RR10_PP1_M1_C1" site2="RR10_PP1_M2_C1"/>
            </ListOfBonds>
          </ProductPattern>
        </ListOfProductPatterns>
        <RateLaw id="RR10_RateLaw" type="Ele" totalrate="0">
          <ListOfRateConstants>
            <RateConstant value="gamma"/>
          </ListOfRateConstants>
        </RateLaw>
        <Map>
          <MapItem sourceID="RR10_RP1_M1" targetID="RR10_PP1_M1"/>
          <MapItem sourceID="RR10_RP1_M1_C1" targetID="RR10_PP1_M1_C1"/>
          <MapItem sourceID="RR10_RP1_M1_C2" targetID="RR10_PP1_M1_C2"/>
          <MapItem sourceID="RR10_RP2_M1" targetID="RR10_PP1_M2"/>
          <MapItem sourceID="RR10_RP2_M1_C1" targetID="RR10_PP1_M2_C1"/>
        </Map>
        <ListOfOperations>
          <AddBond site1="RR10_RP1_M1_C1" site2="RR10_RP2_M1_C1"/>
        </ListOfOperations>
      </ReactionRule>
      <ReactionRule id="RR11" name="degradation_dimer" symmetry_factor="1">
        <ListOfReactantPatterns>
          <ReactantPattern id="RR11_RP1">
            <ListOfMolecules>
              <Molecule id="RR11_RP1_M1" name="A">
                <ListOfComponents>
                  <Component id="RR11_RP1_M1_C1" name="b" numberOfBonds="1"/>
                  <Component id="RR11_RP1_M1_C2" name="gb" numberOfBonds="0"/>
                </ListOfComponents>
              </Molecule>
              <Molecule id="RR11_RP1_M2" name="B">
                <ListOfComponents>
                  <Component id="RR11_RP1_M2_C1" name="a" numberOfBonds="1"/>
                </ListOfComponents>
              </Molecule>
            </ListOfMolecules>
            <ListOfBonds>
              <Bond id="RR11_RP1_B1" site1="RR11_RP1_M1_C1" site2="RR11_RP1_M2_C1"/>
            </ListOfBonds>
          </ReactantPattern>
        </ListOfReactantPatterns>
        <ListOfProductPatterns>
        </ListOfProductPatterns>
        <RateLaw id="RR11_RateLaw" type="Ele" totalrate="0">
          <ListOfRateConstants>
            <RateConstant value="deltaAB"/>
          </ListOfRateConstants>
        </RateLaw>
        <Map>
          <MapItem sourceID="RR11_RP1_M1"/>
          <MapItem sourceID="RR11_RP1_M1_C1"/>
          <MapItem sourceID="RR11_RP1_M1_C2"/>
          <MapItem sourceID="RR11_RP1_M2"/>
          <MapItem sourceID="RR11_RP1_M2_C1"/>
        </Map>
        <ListOfOperations>
          <Delete id="RR11_RP1" DeleteMolecules="0"/>
        </ListOfOperations>
      </ReactionRule>
    </ListOfReactionRules>
    <ListOfObservables>
      <Observable id="O1" name="A" type="Species">
        <ListOfPatterns>
          <Pattern id="O1_P1" matchOnce="1">
            <ListOfMolecules>
              <Molecule id="O1_P1_M1" name="A">
                <ListOfComponents>
                  <Component id="O1_P1_M1_C1" name="b" numberOfBonds="0"/>
                  <Component id="O1_P1_M1_C2" name="gb" numberOfBonds="0"/>
                </ListOfComponents>
              </Molecule>
            </ListOfMolecules>
          </Pattern>
        </ListOfPatterns>
      </Observable>
      <Observable id="O2" name="AgB" type="Species">
        <ListOfPatterns>
          <Pattern id="O2_P1" matchOnce="1">
            <ListOfMolecules>
              <Molecule id="O2_P1_M1" name="A">
                <ListOfComponents>
                  <Component id="O2_P1_M1_C1" name="b" numberOfBonds="0"/>
                  <Component id="O2_P1_M1_C2" name="gb" numberOfBonds="1"/>
                </ListOfComponents>
              </Molecule>
              <Molecule id="O2_P1_M2" name="gB">
                <ListOfComponents>
                  <Component id="O2_P1_M2_C1" name="a" numberOfBonds="1"/>
                </ListOfComponents>
              </Molecule>
            </ListOfMolecules>
            <ListOfBonds>
              <Bond id="O2_P1_B1" site1="O2_P1_M1_C2" site2="O2_P1_M2_C1"/>
            </ListOfBonds>
          </Pattern>
        </ListOfPatterns>
      </Observable>
      <Observable id="O3" name="gB" type="Species">
        <ListOfPatterns>
          <Pattern id="O3_P1" matchOnce="1">
            <ListOfMolecules>
              <Molecule id="O3_P1_M1" name="gB">
                <ListOfComponents>
                  <Component id="O3_P1_M1_C1" name="a" numberOfBonds="0"/>
                </ListOfComponents>
              </Molecule>
            </ListOfMolecules>
          </Pattern>
        </ListOfPatterns>
      </Observable>
      <Observable id="O4" name="rB" type="Species">
        <ListOfPatterns>
          <Pattern id="O4_P1" matchOnce="1">
            <ListOfMolecules>
              <Molecule id="O4_P1_M1" name="rB"/>
            </ListOfMolecules>
          </Pattern>
        </ListOfPatterns>
      </Observable>
      <Observable id="O5" name="B" type="Species">
        <ListOfPatterns>
          <Pattern id="O5_P1" matchOnce="1">
            <ListOfMolecules>
              <Molecule id="O5_P1_M1" name="B">
                <ListOfComponents>
                  <Component id="O5_P1_M1_C1" name="a" numberOfBonds="0"/>
                </ListOfComponents>
              </Molecule>
            </ListOfMolecules>
          </Pattern>
        </ListOfPatterns>
      </Observable>
      <Observable id="O6" name="AB" type="Species">
        <ListOfPatterns>
          <Pattern id="O6_P1" matchOnce="1">
            <ListOfMolecules>
              <Molecule id="O6_P1_M1" name="A">
                <ListOfComponents>
                  <Component id="O6_P1_M1_C1" name="b" numberOfBonds="1"/>
                  <Component id="O6_P1_M1_C2" name="gb" numberOfBonds="0"/>
                </ListOfComponents>
              </Molecule>
              <Molecule id="O6_P1_M2" name="B">
                <ListOfComponents>
                  <Component id="O6_P1_M2_C1" name="a" numberOfBonds="1"/>
                </ListOfComponents>
              </Molecule>
            </ListOfMolecules>
            <ListOfBonds>
              <Bond id="O6_P1_B1" site1="O6_P1_M1_C1" site2="O6_P1_M2_C1"/>
            </ListOfBonds>
          </Pattern>
        </ListOfPatterns>
      </Observable>
    </ListOfObservables>
    <ListOfFunctions>
      <Function id="fRate2">
        <ListOfReferences>
          <Reference name="rhof" type="Constant"/>
          <Reference name="gB" type="Observable"/>
        </ListOfReferences>
        <Expression> gB*rhof </Expression>
      </Function>
      <Function id="fRate3">
        <ListOfReferences>
          <Reference name="rhob" type="Constant"/>
          <Reference name="AgB" type="Observable"/>
        </ListOfReferences>
        <Expression> AgB*rhob </Expression>
      </Function>
      <Function id="fRate7">
        <ListOfReferences>
          <Reference name="beta" type="Constant"/>
          <Reference name="rB" type="Observable"/>
        </ListOfReferences>
        <Expression> beta*rB </Expression>
      </Function>
    </ListOfFunctions>
  </model>
</sbml>
