<?xml version="1.0" encoding="UTF-8"?>
<!-- Created by BioNetGen 2.6.0  -->
<sbml xmlns="http://www.sbml.org/sbml/level3" level="3" version="1">
  <model id="bmd0000000211_flat">
    <ListOfParameters>
      <Parameter id="RaHXK" type="Constant" value="1" expr="1.0"/>
      <Parameter id="RaPFK" type="Constant" value="1" expr="1.0"/>
      <Parameter id="RaPYK" type="Constant" value="1" expr="1.0"/>
      <Parameter id="RaPGAM" type="Constant" value="1" expr="1.0"/>
      <Parameter id="RaENO" type="Constant" value="1" expr="1.0"/>
      <Parameter id="r1_Vmax_v1" type="Constant" value="108.9" expr="108.900000"/>
      <Parameter id="r1_KGlc" type="Constant" value="1" expr="1.000000"/>
      <Parameter id="r1_Alpha_v1" type="Constant" value="0.75" expr="0.750000"/>
      <Parameter id="r2_Vmax_v2" type="Constant" value="1929" expr="1929.000000"/>
      <Parameter id="r2_KGlcInt_v2" type="Constant" value="0.1" expr="0.100000"/>
      <Parameter id="r2_KATPg_v2" type="Constant" value="0.116" expr="0.116000"/>
      <Parameter id="r2_KADPg_v2" type="Constant" value="0.126" expr="0.126000"/>
      <Parameter id="r2_KGlc6P_v2" type="Constant" value="12" expr="12.000000"/>
      <Parameter id="r3_Kms" type="Constant" value="0.4" expr="0.400000"/>
      <Parameter id="r3_Kmp" type="Constant" value="0.12" expr="0.120000"/>
      <Parameter id="r3_Vf" type="Constant" value="1305" expr="1305.000000"/>
      <Parameter id="r3_Vr" type="Constant" value="1305" expr="1305.000000"/>
      <Parameter id="r4_Vmax_v4" type="Constant" value="1708" expr="1708.000000"/>
      <Parameter id="r4_Ki1Fru16BP_v4" type="Constant" value="15.8" expr="15.800000"/>
      <Parameter id="r4_KFru6P_v4" type="Constant" value="0.82" expr="0.820000"/>
      <Parameter id="r4_KATPg_v4" type="Constant" value="0.026" expr="0.026000"/>
      <Parameter id="r4_Ki2Fru16BP_v4" type="Constant" value="10.7" expr="10.700000"/>
      <Parameter id="r5_Vmax_v5" type="Constant" value="560" expr="560.000000"/>
      <Parameter id="r5_Keq_v5" type="Constant" value="0.069" expr="0.069000"/>
      <Parameter id="r5_r_v5" type="Constant" value="1.19" expr="1.190000"/>
      <Parameter id="r5_KGAP_v5" type="Constant" value="0.067" expr="0.067000"/>
      <Parameter id="r5_KGAPi_v5" type="Constant" value="0.098" expr="0.098000"/>
      <Parameter id="r6_Kms" type="Constant" value="1.2" expr="1.200000"/>
      <Parameter id="r6_Kmp" type="Constant" value="0.25" expr="0.250000"/>
      <Parameter id="r6_Vf" type="Constant" value="999.3" expr="999.300000"/>
      <Parameter id="r6_Vr" type="Constant" value="5696.01" expr="5696.010000"/>
      <Parameter id="r7_Vmax_v7" type="Constant" value="720.9" expr="720.900000"/>
      <Parameter id="r7_KGAP_v7" type="Constant" value="0.15" expr="0.150000"/>
      <Parameter id="r7_KNAD_v7" type="Constant" value="0.45" expr="0.450000"/>
      <Parameter id="r7_r_v7" type="Constant" value="0.67" expr="0.670000"/>
      <Parameter id="r7_KBPGA13_v7" type="Constant" value="0.1" expr="0.100000"/>
      <Parameter id="r7_KNADH_v7" type="Constant" value="0.02" expr="0.020000"/>
      <Parameter id="r8_Vmax_v8" type="Constant" value="465" expr="465.000000"/>
      <Parameter id="r8_KDHAPg_v8" type="Constant" value="0.1" expr="0.100000"/>
      <Parameter id="r8_KNADH_v8" type="Constant" value="0.01" expr="0.010000"/>
      <Parameter id="r8_r_v8" type="Constant" value="0.28" expr="0.280000"/>
      <Parameter id="r8_KNAD_v8" type="Constant" value="0.4" expr="0.400000"/>
      <Parameter id="r8_KGly3Pg_v8" type="Constant" value="2" expr="2.000000"/>
      <Parameter id="r9_Km" type="Constant" value="1.7" expr="1.700000"/>
      <Parameter id="r9_V" type="Constant" value="368" expr="368.000000"/>
      <Parameter id="r10_Km" type="Constant" value="1.96" expr="1.960000"/>
      <Parameter id="r10_V" type="Constant" value="200" expr="200.000000"/>
      <Parameter id="r11_Vmax_v11" type="Constant" value="2862" expr="2862.000000"/>
      <Parameter id="r11_KBPGA13_v11" type="Constant" value="0.003" expr="0.003000"/>
      <Parameter id="r11_KADPg_v11" type="Constant" value="0.1" expr="0.100000"/>
      <Parameter id="r11_r_v11" type="Constant" value="0.47" expr="0.470000"/>
      <Parameter id="r11_KPGA3_v11" type="Constant" value="1.62" expr="1.620000"/>
      <Parameter id="r11_KATPg_v11" type="Constant" value="0.29" expr="0.290000"/>
      <Parameter id="r12_Vmax_v12" type="Constant" value="1020" expr="1020.000000"/>
      <Parameter id="r12_PK_n" type="Constant" value="2.5" expr="2.500000"/>
      <Parameter id="r12_KADP_v12" type="Constant" value="0.114" expr="0.114000"/>
      <Parameter id="r13_k" type="Constant" value="50" expr="50.000000"/>
      <Parameter id="r14_Vmax_v14" type="Constant" value="200" expr="200.000000"/>
      <Parameter id="r14_KGly3Pg_v14" type="Constant" value="3.83" expr="3.830000"/>
      <Parameter id="r14_KADPg_v14" type="Constant" value="0.56" expr="0.560000"/>
      <Parameter id="r14_r_v14" type="Constant" value="60.86" expr="60.860000"/>
      <Parameter id="r14_KGlycerol_v14" type="Constant" value="0.44" expr="0.440000"/>
      <Parameter id="r14_KATPg_v14" type="Constant" value="0.24" expr="0.240000"/>
      <Parameter id="r15_Kms" type="Constant" value="0.27" expr="0.270000"/>
      <Parameter id="r15_Kmp" type="Constant" value="0.11" expr="0.110000"/>
      <Parameter id="r15_Vf" type="Constant" value="225" expr="225.000000"/>
      <Parameter id="r15_Vr" type="Constant" value="495" expr="495.000000"/>
      <Parameter id="r16_Kms" type="Constant" value="0.054" expr="0.054000"/>
      <Parameter id="r16_Kmp" type="Constant" value="0.24" expr="0.240000"/>
      <Parameter id="r16_Vf" type="Constant" value="598" expr="598.000000"/>
      <Parameter id="r16_Vr" type="Constant" value="394.68" expr="394.680000"/>
      <Parameter id="r17_k" type="Constant" value="1000000" expr="1000000.000000"/>
      <Parameter id="r17_keqak" type="Constant" value="0.442" expr="0.442000"/>
      <Parameter id="r18_k" type="Constant" value="1000000" expr="1000000.000000"/>
      <Parameter id="r18_keqak" type="Constant" value="0.442" expr="0.442000"/>
      <Parameter id="r19_k1" type="Constant" value="1000000" expr="1000000.000000"/>
      <Parameter id="r19_k2" type="Constant" value="1000000" expr="1000000.000000"/>
      <Parameter id="r20_k1" type="Constant" value="1000000" expr="1000000.000000"/>
      <Parameter id="r20_k2" type="Constant" value="1000000" expr="1000000.000000"/>
      <Parameter id="r21_k1" type="Constant" value="1000000" expr="1000000.000000"/>
      <Parameter id="r21_k2" type="Constant" value="1000000" expr="1000000.000000"/>
    </ListOfParameters>
    <ListOfMoleculeTypes>
      <MoleculeType id="adpc"/>
      <MoleculeType id="adpg"/>
      <MoleculeType id="ampc"/>
      <MoleculeType id="ampg"/>
      <MoleculeType id="atpc"/>
      <MoleculeType id="atpg"/>
      <MoleculeType id="bisphosphoglycerate"/>
      <MoleculeType id="dihydroxyacetonephosphate"/>
      <MoleculeType id="dihydroxyacetonephosphatecytosol"/>
      <MoleculeType id="fructose16bisphosphate"/>
      <MoleculeType id="fructose6phosphate"/>
      <MoleculeType id="glucose"/>
      <MoleculeType id="glucose6phosphate"/>
      <MoleculeType id="glucoseexternal"/>
      <MoleculeType id="glyceraldehyde3phosphate"/>
      <MoleculeType id="glycerol"/>
      <MoleculeType id="glycerol3phosphate"/>
      <MoleculeType id="glycerol3phosphatecytosol"/>
      <MoleculeType id="glycerolexternal"/>
      <MoleculeType id="nad"/>
      <MoleculeType id="nadh"/>
      <MoleculeType id="phosphoenolpyruvate"/>
      <MoleculeType id="pyruvate"/>
      <MoleculeType id="pyruvateexternal"/>
      <MoleculeType id="s2phosphoglycerate"/>
      <MoleculeType id="s3phosphoglycerate"/>
      <MoleculeType id="s3phosphoglyceratecytosol"/>
    </ListOfMoleculeTypes>
    <ListOfCompartments>
      <compartment id="compartment_1" spatialDimensions="3" size="1.0"/>
      <compartment id="compartment_2" spatialDimensions="3" size="1.0"/>
      <compartment id="compartment_3" spatialDimensions="3" size="1.0"/>
    </ListOfCompartments>
    <ListOfSpecies>
      <Species id="S1"  concentration="6.022e+21" name="@compartment_1::pyruvate()" compartment="compartment_1">
        <ListOfMolecules>
          <Molecule id="S1_M1" name="pyruvate" compartment="compartment_1"/>
        </ListOfMolecules>
      </Species>
      <Species id="S2"  concentration="7.928100158577502e+20" name="@compartment_1::adpc()" compartment="compartment_1">
        <ListOfMolecules>
          <Molecule id="S2_M1" name="adpc" compartment="compartment_1"/>
        </ListOfMolecules>
      </Species>
      <Species id="S3"  concentration="2.05794992071125e+20" name="@compartment_1::atpc()" compartment="compartment_1">
        <ListOfMolecules>
          <Molecule id="S3_M1" name="atpc" compartment="compartment_1"/>
        </ListOfMolecules>
      </Species>
      <Species id="S4"  concentration="1.349974992074136e+21" name="@compartment_1::ampc()" compartment="compartment_1">
        <ListOfMolecules>
          <Molecule id="S4_M1" name="ampc" compartment="compartment_1"/>
        </ListOfMolecules>
      </Species>
      <Species id="S5"  concentration="1.343716529813336e+21" name="@compartment_1::dihydroxyacetonephosphatecytosol()" compartment="compartment_1">
        <ListOfMolecules>
          <Molecule id="S5_M1" name="dihydroxyacetonephosphatecytosol" compartment="compartment_1"/>
        </ListOfMolecules>
      </Species>
      <Species id="S6"  concentration="1.667283470186664e+21" name="@compartment_1::glycerol3phosphatecytosol()" compartment="compartment_1">
        <ListOfMolecules>
          <Molecule id="S6_M1" name="glycerol3phosphatecytosol" compartment="compartment_1"/>
        </ListOfMolecules>
      </Species>
      <Species id="S7"  concentration="1.448302185913176e+20" name="@compartment_2::atpg()" compartment="compartment_2">
        <ListOfMolecules>
          <Molecule id="S7_M1" name="atpg" compartment="compartment_2"/>
        </ListOfMolecules>
      </Species>
      <Species id="S8"  concentration="9.14739562814956e+20" name="@compartment_2::adpg()" compartment="compartment_2">
        <ListOfMolecules>
          <Molecule id="S8_M1" name="adpg" compartment="compartment_2"/>
        </ListOfMolecules>
      </Species>
      <Species id="S9"  concentration="2.5536302185925223e+21" name="@compartment_2::ampg()" compartment="compartment_2">
        <ListOfMolecules>
          <Molecule id="S9_M1" name="ampg" compartment="compartment_2"/>
        </ListOfMolecules>
      </Species>
      <Species id="S10"  concentration="3.011e+20" name="@compartment_2::glucose6phosphate()" compartment="compartment_2">
        <ListOfMolecules>
          <Molecule id="S10_M1" name="glucose6phosphate" compartment="compartment_2"/>
        </ListOfMolecules>
      </Species>
      <Species id="S11"  concentration="3.011e+20" name="@compartment_2::fructose6phosphate()" compartment="compartment_2">
        <ListOfMolecules>
          <Molecule id="S11_M1" name="fructose6phosphate" compartment="compartment_2"/>
        </ListOfMolecules>
      </Species>
      <Species id="S12"  concentration="6.022e+21" name="@compartment_2::fructose16bisphosphate()" compartment="compartment_2">
        <ListOfMolecules>
          <Molecule id="S12_M1" name="fructose16bisphosphate" compartment="compartment_2"/>
        </ListOfMolecules>
      </Species>
      <Species id="S13"  concentration="5.106122813282246e+21" name="@compartment_2::dihydroxyacetonephosphate()" compartment="compartment_2">
        <ListOfMolecules>
          <Molecule id="S13_M1" name="dihydroxyacetonephosphate" compartment="compartment_2"/>
        </ListOfMolecules>
      </Species>
      <Species id="S14"  concentration="1.5055e+21" name="@compartment_2::glyceraldehyde3phosphate()" compartment="compartment_2">
        <ListOfMolecules>
          <Molecule id="S14_M1" name="glyceraldehyde3phosphate" compartment="compartment_2"/>
        </ListOfMolecules>
      </Species>
      <Species id="S15"  concentration="1.2044e+21" name="@compartment_2::nad()" compartment="compartment_2">
        <ListOfMolecules>
          <Molecule id="S15_M1" name="nad" compartment="compartment_2"/>
        </ListOfMolecules>
      </Species>
      <Species id="S16"  concentration="1.2044e+21" name="@compartment_2::nadh()" compartment="compartment_2">
        <ListOfMolecules>
          <Molecule id="S16_M1" name="nadh" compartment="compartment_2"/>
        </ListOfMolecules>
      </Species>
      <Species id="S17"  concentration="3.011e+20" name="@compartment_2::bisphosphoglycerate()" compartment="compartment_2">
        <ListOfMolecules>
          <Molecule id="S17_M1" name="bisphosphoglycerate" compartment="compartment_2"/>
        </ListOfMolecules>
      </Species>
      <Species id="S18"  concentration="6.335677186735821e+21" name="@compartment_2::glycerol3phosphate()" compartment="compartment_2">
        <ListOfMolecules>
          <Molecule id="S18_M1" name="glycerol3phosphate" compartment="compartment_2"/>
        </ListOfMolecules>
      </Species>
      <Species id="S19"  concentration="3.011e+21" name="@compartment_3::$glucoseexternal()" compartment="compartment_3" Fixed="1">
        <ListOfMolecules>
          <Molecule id="S19_M1" name="glucoseexternal" compartment="compartment_3"/>
        </ListOfMolecules>
      </Species>
    </ListOfSpecies>
    <ListOfReactionRules>
      <ReactionRule id="RR1" name="vGT" symmetry_factor="1">
        <ListOfReactantPatterns>
          <ReactantPattern id="RR1_RP1">
            <ListOfMolecules>
              <Molecule id="RR1_RP1_M1" name="glucoseexternal" compartment="compartment_3"/>
            </ListOfMolecules>
          </ReactantPattern>
        </ListOfReactantPatterns>
        <ListOfProductPatterns>
          <ProductPattern id="RR1_PP1">
            <ListOfMolecules>
              <Molecule id="RR1_PP1_M1" name="glucose" compartment="compartment_2"/>
            </ListOfMolecules>
          </ProductPattern>
        </ListOfProductPatterns>
        <RateLaw id="RR1_RateLaw" type="Function" name="fRate0" totalrate="0">
          <ListOfArguments>
          </ListOfArguments>
        </RateLaw>
        <Map>
          <MapItem sourceID="RR1_RP1_M1"/>
        </Map>
        <ListOfOperations>
          <Add id="RR1_PP1_M1"/>
          <Delete id="RR1_RP1" DeleteMolecules="0"/>
        </ListOfOperations>
      </ReactionRule>
      <ReactionRule id="RR2" name="_reverse_vGT" symmetry_factor="1">
        <ListOfReactantPatterns>
          <ReactantPattern id="RR2_RP1">
            <ListOfMolecules>
              <Molecule id="RR2_RP1_M1" name="glucose" compartment="compartment_2"/>
            </ListOfMolecules>
          </ReactantPattern>
        </ListOfReactantPatterns>
        <ListOfProductPatterns>
          <ProductPattern id="RR2_PP1">
            <ListOfMolecules>
              <Molecule id="RR2_PP1_M1" name="glucoseexternal" compartment="compartment_3"/>
            </ListOfMolecules>
          </ProductPattern>
        </ListOfProductPatterns>
        <RateLaw id="RR2_RateLaw" type="Function" name="fRate0m" totalrate="0">
          <ListOfArguments>
          </ListOfArguments>
        </RateLaw>
        <Map>
          <MapItem sourceID="RR2_RP1_M1"/>
        </Map>
        <ListOfOperations>
          <Add id="RR2_PP1_M1"/>
          <Delete id="RR2_RP1" DeleteMolecules="0"/>
        </ListOfOperations>
      </ReactionRule>
      <ReactionRule id="RR3" name="vHK" symmetry_factor="1">
        <ListOfReactantPatterns>
          <ReactantPattern id="RR3_RP1">
            <ListOfMolecules>
              <Molecule id="RR3_RP1_M1" name="glucose" compartment="compartment_2"/>
            </ListOfMolecules>
          </ReactantPattern>
          <ReactantPattern id="RR3_RP2">
            <ListOfMolecules>
              <Molecule id="RR3_RP2_M1" name="atpg" compartment="compartment_2"/>
            </ListOfMolecules>
          </ReactantPattern>
        </ListOfReactantPatterns>
        <ListOfProductPatterns>
          <ProductPattern id="RR3_PP1">
            <ListOfMolecules>
              <Molecule id="RR3_PP1_M1" name="glucose6phosphate" compartment="compartment_2"/>
            </ListOfMolecules>
          </ProductPattern>
          <ProductPattern id="RR3_PP2">
            <ListOfMolecules>
              <Molecule id="RR3_PP2_M1" name="adpg" compartment="compartment_2"/>
            </ListOfMolecules>
          </ProductPattern>
        </ListOfProductPatterns>
        <RateLaw id="RR3_RateLaw" type="Function" name="fRate1" totalrate="0">
          <ListOfArguments>
          </ListOfArguments>
        </RateLaw>
        <Map>
          <MapItem sourceID="RR3_RP1_M1"/>
          <MapItem sourceID="RR3_RP2_M1"/>
        </Map>
        <ListOfOperations>
          <Add id="RR3_PP1_M1"/>
          <Add id="RR3_PP2_M1"/>
          <Delete id="RR3_RP1" DeleteMolecules="0"/>
          <Delete id="RR3_RP2" DeleteMolecules="0"/>
        </ListOfOperations>
      </ReactionRule>
      <ReactionRule id="RR4" name="vPGI" symmetry_factor="1">
        <ListOfReactantPatterns>
          <ReactantPattern id="RR4_RP1">
            <ListOfMolecules>
              <Molecule id="RR4_RP1_M1" name="glucose6phosphate" compartment="compartment_2"/>
            </ListOfMolecules>
          </ReactantPattern>
        </ListOfReactantPatterns>
        <ListOfProductPatterns>
          <ProductPattern id="RR4_PP1">
            <ListOfMolecules>
              <Molecule id="RR4_PP1_M1" name="fructose6phosphate" compartment="compartment_2"/>
            </ListOfMolecules>
          </ProductPattern>
        </ListOfProductPatterns>
        <RateLaw id="RR4_RateLaw" type="Function" name="fRate2" totalrate="0">
          <ListOfArguments>
          </ListOfArguments>
        </RateLaw>
        <Map>
          <MapItem sourceID="RR4_RP1_M1"/>
        </Map>
        <ListOfOperations>
          <Add id="RR4_PP1_M1"/>
          <Delete id="RR4_RP1" DeleteMolecules="0"/>
        </ListOfOperations>
      </ReactionRule>
      <ReactionRule id="RR5" name="_reverse_vPGI" symmetry_factor="1">
        <ListOfReactantPatterns>
          <ReactantPattern id="RR5_RP1">
            <ListOfMolecules>
              <Molecule id="RR5_RP1_M1" name="fructose6phosphate" compartment="compartment_2"/>
            </ListOfMolecules>
          </ReactantPattern>
        </ListOfReactantPatterns>
        <ListOfProductPatterns>
          <ProductPattern id="RR5_PP1">
            <ListOfMolecules>
              <Molecule id="RR5_PP1_M1" name="glucose6phosphate" compartment="compartment_2"/>
            </ListOfMolecules>
          </ProductPattern>
        </ListOfProductPatterns>
        <RateLaw id="RR5_RateLaw" type="Function" name="fRate2m" totalrate="0">
          <ListOfArguments>
          </ListOfArguments>
        </RateLaw>
        <Map>
          <MapItem sourceID="RR5_RP1_M1"/>
        </Map>
        <ListOfOperations>
          <Add id="RR5_PP1_M1"/>
          <Delete id="RR5_RP1" DeleteMolecules="0"/>
        </ListOfOperations>
      </ReactionRule>
      <ReactionRule id="RR6" name="vPFK" symmetry_factor="1">
        <ListOfReactantPatterns>
          <ReactantPattern id="RR6_RP1">
            <ListOfMolecules>
              <Molecule id="RR6_RP1_M1" name="fructose6phosphate" compartment="compartment_2"/>
            </ListOfMolecules>
          </ReactantPattern>
          <ReactantPattern id="RR6_RP2">
            <ListOfMolecules>
              <Molecule id="RR6_RP2_M1" name="atpg" compartment="compartment_2"/>
            </ListOfMolecules>
          </ReactantPattern>
        </ListOfReactantPatterns>
        <ListOfProductPatterns>
          <ProductPattern id="RR6_PP1">
            <ListOfMolecules>
              <Molecule id="RR6_PP1_M1" name="fructose16bisphosphate" compartment="compartment_2"/>
            </ListOfMolecules>
          </ProductPattern>
          <ProductPattern id="RR6_PP2">
            <ListOfMolecules>
              <Molecule id="RR6_PP2_M1" name="adpg" compartment="compartment_2"/>
            </ListOfMolecules>
          </ProductPattern>
        </ListOfProductPatterns>
        <RateLaw id="RR6_RateLaw" type="Function" name="fRate3" totalrate="0">
          <ListOfArguments>
          </ListOfArguments>
        </RateLaw>
        <Map>
          <MapItem sourceID="RR6_RP1_M1"/>
          <MapItem sourceID="RR6_RP2_M1"/>
        </Map>
        <ListOfOperations>
          <Add id="RR6_PP1_M1"/>
          <Add id="RR6_PP2_M1"/>
          <Delete id="RR6_RP1" DeleteMolecules="0"/>
          <Delete id="RR6_RP2" DeleteMolecules="0"/>
        </ListOfOperations>
      </ReactionRule>
      <ReactionRule id="RR7" name="vALD" symmetry_factor="1">
        <ListOfReactantPatterns>
          <ReactantPattern id="RR7_RP1">
            <ListOfMolecules>
              <Molecule id="RR7_RP1_M1" name="fructose16bisphosphate" compartment="compartment_2"/>
            </ListOfMolecules>
          </ReactantPattern>
        </ListOfReactantPatterns>
        <ListOfProductPatterns>
          <ProductPattern id="RR7_PP1">
            <ListOfMolecules>
              <Molecule id="RR7_PP1_M1" name="dihydroxyacetonephosphate" compartment="compartment_2"/>
            </ListOfMolecules>
          </ProductPattern>
          <ProductPattern id="RR7_PP2">
            <ListOfMolecules>
              <Molecule id="RR7_PP2_M1" name="glyceraldehyde3phosphate" compartment="compartment_2"/>
            </ListOfMolecules>
          </ProductPattern>
        </ListOfProductPatterns>
        <RateLaw id="RR7_RateLaw" type="Function" name="fRate4" totalrate="0">
          <ListOfArguments>
          </ListOfArguments>
        </RateLaw>
        <Map>
          <MapItem sourceID="RR7_RP1_M1"/>
        </Map>
        <ListOfOperations>
          <Add id="RR7_PP1_M1"/>
          <Add id="RR7_PP2_M1"/>
          <Delete id="RR7_RP1" DeleteMolecules="0"/>
        </ListOfOperations>
      </ReactionRule>
      <ReactionRule id="RR8" name="_reverse_vALD" symmetry_factor="1">
        <ListOfReactantPatterns>
          <ReactantPattern id="RR8_RP1">
            <ListOfMolecules>
              <Molecule id="RR8_RP1_M1" name="dihydroxyacetonephosphate" compartment="compartment_2"/>
            </ListOfMolecules>
          </ReactantPattern>
          <ReactantPattern id="RR8_RP2">
            <ListOfMolecules>
              <Molecule id="RR8_RP2_M1" name="glyceraldehyde3phosphate" compartment="compartment_2"/>
            </ListOfMolecules>
          </ReactantPattern>
        </ListOfReactantPatterns>
        <ListOfProductPatterns>
          <ProductPattern id="RR8_PP1">
            <ListOfMolecules>
              <Molecule id="RR8_PP1_M1" name="fructose16bisphosphate" compartment="compartment_2"/>
            </ListOfMolecules>
          </ProductPattern>
        </ListOfProductPatterns>
        <RateLaw id="RR8_RateLaw" type="Function" name="fRate4m" totalrate="0">
          <ListOfArguments>
          </ListOfArguments>
        </RateLaw>
        <Map>
          <MapItem sourceID="RR8_RP1_M1"/>
          <MapItem sourceID="RR8_RP2_M1"/>
        </Map>
        <ListOfOperations>
          <Add id="RR8_PP1_M1"/>
          <Delete id="RR8_RP1" DeleteMolecules="0"/>
          <Delete id="RR8_RP2" DeleteMolecules="0"/>
        </ListOfOperations>
      </ReactionRule>
      <ReactionRule id="RR9" name="vTPI" symmetry_factor="1">
        <ListOfReactantPatterns>
          <ReactantPattern id="RR9_RP1">
            <ListOfMolecules>
              <Molecule id="RR9_RP1_M1" name="dihydroxyacetonephosphate" compartment="compartment_2"/>
            </ListOfMolecules>
          </ReactantPattern>
        </ListOfReactantPatterns>
        <ListOfProductPatterns>
          <ProductPattern id="RR9_PP1">
            <ListOfMolecules>
              <Molecule id="RR9_PP1_M1" name="glyceraldehyde3phosphate" compartment="compartment_2"/>
            </ListOfMolecules>
          </ProductPattern>
        </ListOfProductPatterns>
        <RateLaw id="RR9_RateLaw" type="Function" name="fRate5" totalrate="0">
          <ListOfArguments>
          </ListOfArguments>
        </RateLaw>
        <Map>
          <MapItem sourceID="RR9_RP1_M1"/>
        </Map>
        <ListOfOperations>
          <Add id="RR9_PP1_M1"/>
          <Delete id="RR9_RP1" DeleteMolecules="0"/>
        </ListOfOperations>
      </ReactionRule>
      <ReactionRule id="RR10" name="_reverse_vTPI" symmetry_factor="1">
        <ListOfReactantPatterns>
          <ReactantPattern id="RR10_RP1">
            <ListOfMolecules>
              <Molecule id="RR10_RP1_M1" name="glyceraldehyde3phosphate" compartment="compartment_2"/>
            </ListOfMolecules>
          </ReactantPattern>
        </ListOfReactantPatterns>
        <ListOfProductPatterns>
          <ProductPattern id="RR10_PP1">
            <ListOfMolecules>
              <Molecule id="RR10_PP1_M1" name="dihydroxyacetonephosphate" compartment="compartment_2"/>
            </ListOfMolecules>
          </ProductPattern>
        </ListOfProductPatterns>
        <RateLaw id="RR10_RateLaw" type="Function" name="fRate5m" totalrate="0">
          <ListOfArguments>
          </ListOfArguments>
        </RateLaw>
        <Map>
          <MapItem sourceID="RR10_RP1_M1"/>
        </Map>
        <ListOfOperations>
          <Add id="RR10_PP1_M1"/>
          <Delete id="RR10_RP1" DeleteMolecules="0"/>
        </ListOfOperations>
      </ReactionRule>
      <ReactionRule id="RR11" name="vGAPDH" symmetry_factor="1">
        <ListOfReactantPatterns>
          <ReactantPattern id="RR11_RP1">
            <ListOfMolecules>
              <Molecule id="RR11_RP1_M1" name="glyceraldehyde3phosphate" compartment="compartment_2"/>
            </ListOfMolecules>
          </ReactantPattern>
          <ReactantPattern id="RR11_RP2">
            <ListOfMolecules>
              <Molecule id="RR11_RP2_M1" name="nad" compartment="compartment_2"/>
            </ListOfMolecules>
          </ReactantPattern>
        </ListOfReactantPatterns>
        <ListOfProductPatterns>
          <ProductPattern id="RR11_PP1">
            <ListOfMolecules>
              <Molecule id="RR11_PP1_M1" name="bisphosphoglycerate" compartment="compartment_2"/>
            </ListOfMolecules>
          </ProductPattern>
          <ProductPattern id="RR11_PP2">
            <ListOfMolecules>
              <Molecule id="RR11_PP2_M1" name="nadh" compartment="compartment_2"/>
            </ListOfMolecules>
          </ProductPattern>
        </ListOfProductPatterns>
        <RateLaw id="RR11_RateLaw" type="Function" name="fRate6" totalrate="0">
          <ListOfArguments>
          </ListOfArguments>
        </RateLaw>
        <Map>
          <MapItem sourceID="RR11_RP1_M1"/>
          <MapItem sourceID="RR11_RP2_M1"/>
        </Map>
        <ListOfOperations>
          <Add id="RR11_PP1_M1"/>
          <Add id="RR11_PP2_M1"/>
          <Delete id="RR11_RP1" DeleteMolecules="0"/>
          <Delete id="RR11_RP2" DeleteMolecules="0"/>
        </ListOfOperations>
      </ReactionRule>
      <ReactionRule id="RR12" name="_reverse_vGAPDH" symmetry_factor="1">
        <ListOfReactantPatterns>
          <ReactantPattern id="RR12_RP1">
            <ListOfMolecules>
              <Molecule id="RR12_RP1_M1" name="bisphosphoglycerate" compartment="compartment_2"/>
            </ListOfMolecules>
          </ReactantPattern>
          <ReactantPattern id="RR12_RP2">
            <ListOfMolecules>
              <Molecule id="RR12_RP2_M1" name="nadh" compartment="compartment_2"/>
            </ListOfMolecules>
          </ReactantPattern>
        </ListOfReactantPatterns>
        <ListOfProductPatterns>
          <ProductPattern id="RR12_PP1">
            <ListOfMolecules>
              <Molecule id="RR12_PP1_M1" name="glyceraldehyde3phosphate" compartment="compartment_2"/>
            </ListOfMolecules>
          </ProductPattern>
          <ProductPattern id="RR12_PP2">
            <ListOfMolecules>
              <Molecule id="RR12_PP2_M1" name="nad" compartment="compartment_2"/>
            </ListOfMolecules>
          </ProductPattern>
        </ListOfProductPatterns>
        <RateLaw id="RR12_RateLaw" type="Function" name="fRate6m" totalrate="0">
          <ListOfArguments>
          </ListOfArguments>
        </RateLaw>
        <Map>
          <MapItem sourceID="RR12_RP1_M1"/>
          <MapItem sourceID="RR12_RP2_M1"/>
        </Map>
        <ListOfOperations>
          <Add id="RR12_PP1_M1"/>
          <Add id="RR12_PP2_M1"/>
          <Delete id="RR12_RP1" DeleteMolecules="0"/>
          <Delete id="RR12_RP2" DeleteMolecules="0"/>
        </ListOfOperations>
      </ReactionRule>
      <ReactionRule id="RR13" name="vGPDH" symmetry_factor="1">
        <ListOfReactantPatterns>
          <ReactantPattern id="RR13_RP1">
            <ListOfMolecules>
              <Molecule id="RR13_RP1_M1" name="dihydroxyacetonephosphate" compartment="compartment_2"/>
            </ListOfMolecules>
          </ReactantPattern>
          <ReactantPattern id="RR13_RP2">
            <ListOfMolecules>
              <Molecule id="RR13_RP2_M1" name="nadh" compartment="compartment_2"/>
            </ListOfMolecules>
          </ReactantPattern>
        </ListOfReactantPatterns>
        <ListOfProductPatterns>
          <ProductPattern id="RR13_PP1">
            <ListOfMolecules>
              <Molecule id="RR13_PP1_M1" name="nad" compartment="compartment_2"/>
            </ListOfMolecules>
          </ProductPattern>
          <ProductPattern id="RR13_PP2">
            <ListOfMolecules>
              <Molecule id="RR13_PP2_M1" name="glycerol3phosphate" compartment="compartment_2"/>
            </ListOfMolecules>
          </ProductPattern>
        </ListOfProductPatterns>
        <RateLaw id="RR13_RateLaw" type="Function" name="fRate7" totalrate="0">
          <ListOfArguments>
          </ListOfArguments>
        </RateLaw>
        <Map>
          <MapItem sourceID="RR13_RP1_M1"/>
          <MapItem sourceID="RR13_RP2_M1"/>
        </Map>
        <ListOfOperations>
          <Add id="RR13_PP1_M1"/>
          <Add id="RR13_PP2_M1"/>
          <Delete id="RR13_RP1" DeleteMolecules="0"/>
          <Delete id="RR13_RP2" DeleteMolecules="0"/>
        </ListOfOperations>
      </ReactionRule>
      <ReactionRule id="RR14" name="_reverse_vGPDH" symmetry_factor="1">
        <ListOfReactantPatterns>
          <ReactantPattern id="RR14_RP1">
            <ListOfMolecules>
              <Molecule id="RR14_RP1_M1" name="nad" compartment="compartment_2"/>
            </ListOfMolecules>
          </ReactantPattern>
          <ReactantPattern id="RR14_RP2">
            <ListOfMolecules>
              <Molecule id="RR14_RP2_M1" name="glycerol3phosphate" compartment="compartment_2"/>
            </ListOfMolecules>
          </ReactantPattern>
        </ListOfReactantPatterns>
        <ListOfProductPatterns>
          <ProductPattern id="RR14_PP1">
            <ListOfMolecules>
              <Molecule id="RR14_PP1_M1" name="dihydroxyacetonephosphate" compartment="compartment_2"/>
            </ListOfMolecules>
          </ProductPattern>
          <ProductPattern id="RR14_PP2">
            <ListOfMolecules>
              <Molecule id="RR14_PP2_M1" name="nadh" compartment="compartment_2"/>
            </ListOfMolecules>
          </ProductPattern>
        </ListOfProductPatterns>
        <RateLaw id="RR14_RateLaw" type="Function" name="fRate7m" totalrate="0">
          <ListOfArguments>
          </ListOfArguments>
        </RateLaw>
        <Map>
          <MapItem sourceID="RR14_RP1_M1"/>
          <MapItem sourceID="RR14_RP2_M1"/>
        </Map>
        <ListOfOperations>
          <Add id="RR14_PP1_M1"/>
          <Add id="RR14_PP2_M1"/>
          <Delete id="RR14_RP1" DeleteMolecules="0"/>
          <Delete id="RR14_RP2" DeleteMolecules="0"/>
        </ListOfOperations>
      </ReactionRule>
      <ReactionRule id="RR15" name="vGPO" symmetry_factor="1">
        <ListOfReactantPatterns>
          <ReactantPattern id="RR15_RP1">
            <ListOfMolecules>
              <Molecule id="RR15_RP1_M1" name="glycerol3phosphatecytosol" compartment="compartment_1"/>
            </ListOfMolecules>
          </ReactantPattern>
        </ListOfReactantPatterns>
        <ListOfProductPatterns>
          <ProductPattern id="RR15_PP1">
            <ListOfMolecules>
              <Molecule id="RR15_PP1_M1" name="dihydroxyacetonephosphatecytosol" compartment="compartment_1"/>
            </ListOfMolecules>
          </ProductPattern>
        </ListOfProductPatterns>
        <RateLaw id="RR15_RateLaw" type="Function" name="fRate8" totalrate="0">
          <ListOfArguments>
          </ListOfArguments>
        </RateLaw>
        <Map>
          <MapItem sourceID="RR15_RP1_M1"/>
        </Map>
        <ListOfOperations>
          <Add id="RR15_PP1_M1"/>
          <Delete id="RR15_RP1" DeleteMolecules="0"/>
        </ListOfOperations>
      </ReactionRule>
      <ReactionRule id="RR16" name="vPT" symmetry_factor="1">
        <ListOfReactantPatterns>
          <ReactantPattern id="RR16_RP1">
            <ListOfMolecules>
              <Molecule id="RR16_RP1_M1" name="pyruvate" compartment="compartment_1"/>
            </ListOfMolecules>
          </ReactantPattern>
        </ListOfReactantPatterns>
        <ListOfProductPatterns>
          <ProductPattern id="RR16_PP1">
            <ListOfMolecules>
              <Molecule id="RR16_PP1_M1" name="pyruvateexternal" compartment="compartment_3"/>
            </ListOfMolecules>
          </ProductPattern>
        </ListOfProductPatterns>
        <RateLaw id="RR16_RateLaw" type="Function" name="fRate9" totalrate="0">
          <ListOfArguments>
          </ListOfArguments>
        </RateLaw>
        <Map>
          <MapItem sourceID="RR16_RP1_M1"/>
        </Map>
        <ListOfOperations>
          <Add id="RR16_PP1_M1"/>
          <Delete id="RR16_RP1" DeleteMolecules="0"/>
        </ListOfOperations>
      </ReactionRule>
      <ReactionRule id="RR17" name="vPGK" symmetry_factor="1">
        <ListOfReactantPatterns>
          <ReactantPattern id="RR17_RP1">
            <ListOfMolecules>
              <Molecule id="RR17_RP1_M1" name="bisphosphoglycerate" compartment="compartment_2"/>
            </ListOfMolecules>
          </ReactantPattern>
          <ReactantPattern id="RR17_RP2">
            <ListOfMolecules>
              <Molecule id="RR17_RP2_M1" name="adpg" compartment="compartment_2"/>
            </ListOfMolecules>
          </ReactantPattern>
        </ListOfReactantPatterns>
        <ListOfProductPatterns>
          <ProductPattern id="RR17_PP1">
            <ListOfMolecules>
              <Molecule id="RR17_PP1_M1" name="s3phosphoglycerate" compartment="compartment_2"/>
            </ListOfMolecules>
          </ProductPattern>
          <ProductPattern id="RR17_PP2">
            <ListOfMolecules>
              <Molecule id="RR17_PP2_M1" name="atpg" compartment="compartment_2"/>
            </ListOfMolecules>
          </ProductPattern>
        </ListOfProductPatterns>
        <RateLaw id="RR17_RateLaw" type="Function" name="fRate10" totalrate="0">
          <ListOfArguments>
          </ListOfArguments>
        </RateLaw>
        <Map>
          <MapItem sourceID="RR17_RP1_M1"/>
          <MapItem sourceID="RR17_RP2_M1"/>
        </Map>
        <ListOfOperations>
          <Add id="RR17_PP1_M1"/>
          <Add id="RR17_PP2_M1"/>
          <Delete id="RR17_RP1" DeleteMolecules="0"/>
          <Delete id="RR17_RP2" DeleteMolecules="0"/>
        </ListOfOperations>
      </ReactionRule>
      <ReactionRule id="RR18" name="_reverse_vPGK" symmetry_factor="1">
        <ListOfReactantPatterns>
          <ReactantPattern id="RR18_RP1">
            <ListOfMolecules>
              <Molecule id="RR18_RP1_M1" name="s3phosphoglycerate" compartment="compartment_2"/>
            </ListOfMolecules>
          </ReactantPattern>
          <ReactantPattern id="RR18_RP2">
            <ListOfMolecules>
              <Molecule id="RR18_RP2_M1" name="atpg" compartment="compartment_2"/>
            </ListOfMolecules>
          </ReactantPattern>
        </ListOfReactantPatterns>
        <ListOfProductPatterns>
          <ProductPattern id="RR18_PP1">
            <ListOfMolecules>
              <Molecule id="RR18_PP1_M1" name="bisphosphoglycerate" compartment="compartment_2"/>
            </ListOfMolecules>
          </ProductPattern>
          <ProductPattern id="RR18_PP2">
            <ListOfMolecules>
              <Molecule id="RR18_PP2_M1" name="adpg" compartment="compartment_2"/>
            </ListOfMolecules>
          </ProductPattern>
        </ListOfProductPatterns>
        <RateLaw id="RR18_RateLaw" type="Function" name="fRate10m" totalrate="0">
          <ListOfArguments>
          </ListOfArguments>
        </RateLaw>
        <Map>
          <MapItem sourceID="RR18_RP1_M1"/>
          <MapItem sourceID="RR18_RP2_M1"/>
        </Map>
        <ListOfOperations>
          <Add id="RR18_PP1_M1"/>
          <Add id="RR18_PP2_M1"/>
          <Delete id="RR18_RP1" DeleteMolecules="0"/>
          <Delete id="RR18_RP2" DeleteMolecules="0"/>
        </ListOfOperations>
      </ReactionRule>
      <ReactionRule id="RR19" name="vPK_reactants_0" symmetry_factor="1">
        <ListOfReactantPatterns>
        </ListOfReactantPatterns>
        <ListOfProductPatterns>
          <ProductPattern id="RR19_PP1">
            <ListOfMolecules>
              <Molecule id="RR19_PP1_M1" name="phosphoenolpyruvate" compartment="compartment_1"/>
            </ListOfMolecules>
          </ProductPattern>
        </ListOfProductPatterns>
        <RateLaw id="RR19_RateLaw" type="Function" name="_rateLaw1" totalrate="0">
          <ListOfArguments>
          </ListOfArguments>
        </RateLaw>
        <Map>
        </Map>
        <ListOfOperations>
          <Add id="RR19_PP1_M1"/>
        </ListOfOperations>
      </ReactionRule>
      <ReactionRule id="RR20" name="vPK_reactants_1" symmetry_factor="1">
        <ListOfReactantPatterns>
        </ListOfReactantPatterns>
        <ListOfProductPatterns>
          <ProductPattern id="RR20_PP1">
            <ListOfMolecules>
              <Molecule id="RR20_PP1_M1" name="adpc" compartment="compartment_1"/>
            </ListOfMolecules>
          </ProductPattern>
        </ListOfProductPatterns>
        <RateLaw id="RR20_RateLaw" type="Function" name="_rateLaw2" totalrate="0">
          <ListOfArguments>
          </ListOfArguments>
        </RateLaw>
        <Map>
        </Map>
        <ListOfOperations>
          <Add id="RR20_PP1_M1"/>
        </ListOfOperations>
      </ReactionRule>
      <ReactionRule id="RR21" name="vPK_products_0" symmetry_factor="1">
        <ListOfReactantPatterns>
        </ListOfReactantPatterns>
        <ListOfProductPatterns>
          <ProductPattern id="RR21_PP1">
            <ListOfMolecules>
              <Molecule id="RR21_PP1_M1" name="pyruvate" compartment="compartment_1"/>
            </ListOfMolecules>
          </ProductPattern>
        </ListOfProductPatterns>
        <RateLaw id="RR21_RateLaw" type="Function" name="fRate11" totalrate="0">
          <ListOfArguments>
          </ListOfArguments>
        </RateLaw>
        <Map>
        </Map>
        <ListOfOperations>
          <Add id="RR21_PP1_M1"/>
        </ListOfOperations>
      </ReactionRule>
      <ReactionRule id="RR22" name="vPK_products_1" symmetry_factor="1">
        <ListOfReactantPatterns>
        </ListOfReactantPatterns>
        <ListOfProductPatterns>
          <ProductPattern id="RR22_PP1">
            <ListOfMolecules>
              <Molecule id="RR22_PP1_M1" name="atpc" compartment="compartment_1"/>
            </ListOfMolecules>
          </ProductPattern>
        </ListOfProductPatterns>
        <RateLaw id="RR22_RateLaw" type="Function" name="fRate11" totalrate="0">
          <ListOfArguments>
          </ListOfArguments>
        </RateLaw>
        <Map>
        </Map>
        <ListOfOperations>
          <Add id="RR22_PP1_M1"/>
        </ListOfOperations>
      </ReactionRule>
      <ReactionRule id="RR23" name="vAU" symmetry_factor="1">
        <ListOfReactantPatterns>
          <ReactantPattern id="RR23_RP1">
            <ListOfMolecules>
              <Molecule id="RR23_RP1_M1" name="atpc" compartment="compartment_1"/>
            </ListOfMolecules>
          </ReactantPattern>
        </ListOfReactantPatterns>
        <ListOfProductPatterns>
          <ProductPattern id="RR23_PP1">
            <ListOfMolecules>
              <Molecule id="RR23_PP1_M1" name="adpc" compartment="compartment_1"/>
            </ListOfMolecules>
          </ProductPattern>
        </ListOfProductPatterns>
        <RateLaw id="RR23_RateLaw" type="Function" name="fRate12" totalrate="0">
          <ListOfArguments>
          </ListOfArguments>
        </RateLaw>
        <Map>
          <MapItem sourceID="RR23_RP1_M1"/>
        </Map>
        <ListOfOperations>
          <Add id="RR23_PP1_M1"/>
          <Delete id="RR23_RP1" DeleteMolecules="0"/>
        </ListOfOperations>
      </ReactionRule>
      <ReactionRule id="RR24" name="vGK" symmetry_factor="1">
        <ListOfReactantPatterns>
          <ReactantPattern id="RR24_RP1">
            <ListOfMolecules>
              <Molecule id="RR24_RP1_M1" name="glycerol3phosphate" compartment="compartment_2"/>
            </ListOfMolecules>
          </ReactantPattern>
          <ReactantPattern id="RR24_RP2">
            <ListOfMolecules>
              <Molecule id="RR24_RP2_M1" name="adpg" compartment="compartment_2"/>
            </ListOfMolecules>
          </ReactantPattern>
        </ListOfReactantPatterns>
        <ListOfProductPatterns>
          <ProductPattern id="RR24_PP1">
            <ListOfMolecules>
              <Molecule id="RR24_PP1_M1" name="glycerol" compartment="compartment_2"/>
            </ListOfMolecules>
          </ProductPattern>
          <ProductPattern id="RR24_PP2">
            <ListOfMolecules>
              <Molecule id="RR24_PP2_M1" name="atpg" compartment="compartment_2"/>
            </ListOfMolecules>
          </ProductPattern>
        </ListOfProductPatterns>
        <RateLaw id="RR24_RateLaw" type="Function" name="fRate13" totalrate="0">
          <ListOfArguments>
          </ListOfArguments>
        </RateLaw>
        <Map>
          <MapItem sourceID="RR24_RP1_M1"/>
          <MapItem sourceID="RR24_RP2_M1"/>
        </Map>
        <ListOfOperations>
          <Add id="RR24_PP1_M1"/>
          <Add id="RR24_PP2_M1"/>
          <Delete id="RR24_RP1" DeleteMolecules="0"/>
          <Delete id="RR24_RP2" DeleteMolecules="0"/>
        </ListOfOperations>
      </ReactionRule>
      <ReactionRule id="RR25" name="_reverse_vGK" symmetry_factor="1">
        <ListOfReactantPatterns>
          <ReactantPattern id="RR25_RP1">
            <ListOfMolecules>
              <Molecule id="RR25_RP1_M1" name="glycerol" compartment="compartment_2"/>
            </ListOfMolecules>
          </ReactantPattern>
          <ReactantPattern id="RR25_RP2">
            <ListOfMolecules>
              <Molecule id="RR25_RP2_M1" name="atpg" compartment="compartment_2"/>
            </ListOfMolecules>
          </ReactantPattern>
        </ListOfReactantPatterns>
        <ListOfProductPatterns>
          <ProductPattern id="RR25_PP1">
            <ListOfMolecules>
              <Molecule id="RR25_PP1_M1" name="glycerol3phosphate" compartment="compartment_2"/>
            </ListOfMolecules>
          </ProductPattern>
          <ProductPattern id="RR25_PP2">
            <ListOfMolecules>
              <Molecule id="RR25_PP2_M1" name="adpg" compartment="compartment_2"/>
            </ListOfMolecules>
          </ProductPattern>
        </ListOfProductPatterns>
        <RateLaw id="RR25_RateLaw" type="Function" name="fRate13m" totalrate="0">
          <ListOfArguments>
          </ListOfArguments>
        </RateLaw>
        <Map>
          <MapItem sourceID="RR25_RP1_M1"/>
          <MapItem sourceID="RR25_RP2_M1"/>
        </Map>
        <ListOfOperations>
          <Add id="RR25_PP1_M1"/>
          <Add id="RR25_PP2_M1"/>
          <Delete id="RR25_RP1" DeleteMolecules="0"/>
          <Delete id="RR25_RP2" DeleteMolecules="0"/>
        </ListOfOperations>
      </ReactionRule>
      <ReactionRule id="RR26" name="vPGM" symmetry_factor="1">
        <ListOfReactantPatterns>
          <ReactantPattern id="RR26_RP1">
            <ListOfMolecules>
              <Molecule id="RR26_RP1_M1" name="s3phosphoglyceratecytosol" compartment="compartment_1"/>
            </ListOfMolecules>
          </ReactantPattern>
        </ListOfReactantPatterns>
        <ListOfProductPatterns>
          <ProductPattern id="RR26_PP1">
            <ListOfMolecules>
              <Molecule id="RR26_PP1_M1" name="s2phosphoglycerate" compartment="compartment_1"/>
            </ListOfMolecules>
          </ProductPattern>
        </ListOfProductPatterns>
        <RateLaw id="RR26_RateLaw" type="Function" name="fRate14" totalrate="0">
          <ListOfArguments>
          </ListOfArguments>
        </RateLaw>
        <Map>
          <MapItem sourceID="RR26_RP1_M1"/>
        </Map>
        <ListOfOperations>
          <Add id="RR26_PP1_M1"/>
          <Delete id="RR26_RP1" DeleteMolecules="0"/>
        </ListOfOperations>
      </ReactionRule>
      <ReactionRule id="RR27" name="_reverse_vPGM" symmetry_factor="1">
        <ListOfReactantPatterns>
          <ReactantPattern id="RR27_RP1">
            <ListOfMolecules>
              <Molecule id="RR27_RP1_M1" name="s2phosphoglycerate" compartment="compartment_1"/>
            </ListOfMolecules>
          </ReactantPattern>
        </ListOfReactantPatterns>
        <ListOfProductPatterns>
          <ProductPattern id="RR27_PP1">
            <ListOfMolecules>
              <Molecule id="RR27_PP1_M1" name="s3phosphoglyceratecytosol" compartment="compartment_1"/>
            </ListOfMolecules>
          </ProductPattern>
        </ListOfProductPatterns>
        <RateLaw id="RR27_RateLaw" type="Function" name="fRate14m" totalrate="0">
          <ListOfArguments>
          </ListOfArguments>
        </RateLaw>
        <Map>
          <MapItem sourceID="RR27_RP1_M1"/>
        </Map>
        <ListOfOperations>
          <Add id="RR27_PP1_M1"/>
          <Delete id="RR27_RP1" DeleteMolecules="0"/>
        </ListOfOperations>
      </ReactionRule>
      <ReactionRule id="RR28" name="vENO" symmetry_factor="1">
        <ListOfReactantPatterns>
          <ReactantPattern id="RR28_RP1">
            <ListOfMolecules>
              <Molecule id="RR28_RP1_M1" name="s2phosphoglycerate" compartment="compartment_1"/>
            </ListOfMolecules>
          </ReactantPattern>
        </ListOfReactantPatterns>
        <ListOfProductPatterns>
          <ProductPattern id="RR28_PP1">
            <ListOfMolecules>
              <Molecule id="RR28_PP1_M1" name="phosphoenolpyruvate" compartment="compartment_1"/>
            </ListOfMolecules>
          </ProductPattern>
        </ListOfProductPatterns>
        <RateLaw id="RR28_RateLaw" type="Function" name="fRate15" totalrate="0">
          <ListOfArguments>
          </ListOfArguments>
        </RateLaw>
        <Map>
          <MapItem sourceID="RR28_RP1_M1"/>
        </Map>
        <ListOfOperations>
          <Add id="RR28_PP1_M1"/>
          <Delete id="RR28_RP1" DeleteMolecules="0"/>
        </ListOfOperations>
      </ReactionRule>
      <ReactionRule id="RR29" name="_reverse_vENO" symmetry_factor="1">
        <ListOfReactantPatterns>
          <ReactantPattern id="RR29_RP1">
            <ListOfMolecules>
              <Molecule id="RR29_RP1_M1" name="phosphoenolpyruvate" compartment="compartment_1"/>
            </ListOfMolecules>
          </ReactantPattern>
        </ListOfReactantPatterns>
        <ListOfProductPatterns>
          <ProductPattern id="RR29_PP1">
            <ListOfMolecules>
              <Molecule id="RR29_PP1_M1" name="s2phosphoglycerate" compartment="compartment_1"/>
            </ListOfMolecules>
          </ProductPattern>
        </ListOfProductPatterns>
        <RateLaw id="RR29_RateLaw" type="Function" name="fRate15m" totalrate="0">
          <ListOfArguments>
          </ListOfArguments>
        </RateLaw>
        <Map>
          <MapItem sourceID="RR29_RP1_M1"/>
        </Map>
        <ListOfOperations>
          <Add id="RR29_PP1_M1"/>
          <Delete id="RR29_RP1" DeleteMolecules="0"/>
        </ListOfOperations>
      </ReactionRule>
      <ReactionRule id="RR30" name="vAKc" symmetry_factor="1">
        <ListOfReactantPatterns>
          <ReactantPattern id="RR30_RP1">
            <ListOfMolecules>
              <Molecule id="RR30_RP1_M1" name="atpc" compartment="compartment_1"/>
            </ListOfMolecules>
          </ReactantPattern>
          <ReactantPattern id="RR30_RP2">
            <ListOfMolecules>
              <Molecule id="RR30_RP2_M1" name="ampc" compartment="compartment_1"/>
            </ListOfMolecules>
          </ReactantPattern>
        </ListOfReactantPatterns>
        <ListOfProductPatterns>
          <ProductPattern id="RR30_PP1">
            <ListOfMolecules>
              <Molecule id="RR30_PP1_M1" name="adpc" compartment="compartment_1"/>
            </ListOfMolecules>
          </ProductPattern>
          <ProductPattern id="RR30_PP2">
            <ListOfMolecules>
              <Molecule id="RR30_PP2_M1" name="adpc" compartment="compartment_1"/>
            </ListOfMolecules>
          </ProductPattern>
        </ListOfProductPatterns>
        <RateLaw id="RR30_RateLaw" type="Ele" totalrate="0">
          <ListOfRateConstants>
            <RateConstant value="r17_k"/>
          </ListOfRateConstants>
        </RateLaw>
        <Map>
          <MapItem sourceID="RR30_RP1_M1"/>
          <MapItem sourceID="RR30_RP2_M1"/>
        </Map>
        <ListOfOperations>
          <Add id="RR30_PP1_M1"/>
          <Add id="RR30_PP2_M1"/>
          <Delete id="RR30_RP1" DeleteMolecules="0"/>
          <Delete id="RR30_RP2" DeleteMolecules="0"/>
        </ListOfOperations>
      </ReactionRule>
      <ReactionRule id="RR31" name="_reverse_vAKc" symmetry_factor="0.5">
        <ListOfReactantPatterns>
          <ReactantPattern id="RR31_RP1">
            <ListOfMolecules>
              <Molecule id="RR31_RP1_M1" name="adpc" compartment="compartment_1"/>
            </ListOfMolecules>
          </ReactantPattern>
          <ReactantPattern id="RR31_RP2">
            <ListOfMolecules>
              <Molecule id="RR31_RP2_M1" name="adpc" compartment="compartment_1"/>
            </ListOfMolecules>
          </ReactantPattern>
        </ListOfReactantPatterns>
        <ListOfProductPatterns>
          <ProductPattern id="RR31_PP1">
            <ListOfMolecules>
              <Molecule id="RR31_PP1_M1" name="atpc" compartment="compartment_1"/>
            </ListOfMolecules>
          </ProductPattern>
          <ProductPattern id="RR31_PP2">
            <ListOfMolecules>
              <Molecule id="RR31_PP2_M1" name="ampc" compartment="compartment_1"/>
            </ListOfMolecules>
          </ProductPattern>
        </ListOfProductPatterns>
        <RateLaw id="RR31_RateLaw" type="Function" name="fRate16m" totalrate="0">
          <ListOfArguments>
          </ListOfArguments>
        </RateLaw>
        <Map>
          <MapItem sourceID="RR31_RP1_M1"/>
          <MapItem sourceID="RR31_RP2_M1"/>
        </Map>
        <ListOfOperations>
          <Add id="RR31_PP1_M1"/>
          <Add id="RR31_PP2_M1"/>
          <Delete id="RR31_RP1" DeleteMolecules="0"/>
          <Delete id="RR31_RP2" DeleteMolecules="0"/>
        </ListOfOperations>
      </ReactionRule>
      <ReactionRule id="RR32" name="vAKg" symmetry_factor="1">
        <ListOfReactantPatterns>
          <ReactantPattern id="RR32_RP1">
            <ListOfMolecules>
              <Molecule id="RR32_RP1_M1" name="atpg" compartment="compartment_2"/>
            </ListOfMolecules>
          </ReactantPattern>
          <ReactantPattern id="RR32_RP2">
            <ListOfMolecules>
              <Molecule id="RR32_RP2_M1" name="ampg" compartment="compartment_2"/>
            </ListOfMolecules>
          </ReactantPattern>
        </ListOfReactantPatterns>
        <ListOfProductPatterns>
          <ProductPattern id="RR32_PP1">
            <ListOfMolecules>
              <Molecule id="RR32_PP1_M1" name="adpg" compartment="compartment_2"/>
            </ListOfMolecules>
          </ProductPattern>
          <ProductPattern id="RR32_PP2">
            <ListOfMolecules>
              <Molecule id="RR32_PP2_M1" name="adpg" compartment="compartment_2"/>
            </ListOfMolecules>
          </ProductPattern>
        </ListOfProductPatterns>
        <RateLaw id="RR32_RateLaw" type="Ele" totalrate="0">
          <ListOfRateConstants>
            <RateConstant value="r18_k"/>
          </ListOfRateConstants>
        </RateLaw>
        <Map>
          <MapItem sourceID="RR32_RP1_M1"/>
          <MapItem sourceID="RR32_RP2_M1"/>
        </Map>
        <ListOfOperations>
          <Add id="RR32_PP1_M1"/>
          <Add id="RR32_PP2_M1"/>
          <Delete id="RR32_RP1" DeleteMolecules="0"/>
          <Delete id="RR32_RP2" DeleteMolecules="0"/>
        </ListOfOperations>
      </ReactionRule>
      <ReactionRule id="RR33" name="_reverse_vAKg" symmetry_factor="0.5">
        <ListOfReactantPatterns>
          <ReactantPattern id="RR33_RP1">
            <ListOfMolecules>
              <Molecule id="RR33_RP1_M1" name="adpg" compartment="compartment_2"/>
            </ListOfMolecules>
          </ReactantPattern>
          <ReactantPattern id="RR33_RP2">
            <ListOfMolecules>
              <Molecule id="RR33_RP2_M1" name="adpg" compartment="compartment_2"/>
            </ListOfMolecules>
          </ReactantPattern>
        </ListOfReactantPatterns>
        <ListOfProductPatterns>
          <ProductPattern id="RR33_PP1">
            <ListOfMolecules>
              <Molecule id="RR33_PP1_M1" name="atpg" compartment="compartment_2"/>
            </ListOfMolecules>
          </ProductPattern>
          <ProductPattern id="RR33_PP2">
            <ListOfMolecules>
              <Molecule id="RR33_PP2_M1" name="ampg" compartment="compartment_2"/>
            </ListOfMolecules>
          </ProductPattern>
        </ListOfProductPatterns>
        <RateLaw id="RR33_RateLaw" type="Function" name="fRate17m" totalrate="0">
          <ListOfArguments>
          </ListOfArguments>
        </RateLaw>
        <Map>
          <MapItem sourceID="RR33_RP1_M1"/>
          <MapItem sourceID="RR33_RP2_M1"/>
        </Map>
        <ListOfOperations>
          <Add id="RR33_PP1_M1"/>
          <Add id="RR33_PP2_M1"/>
          <Delete id="RR33_RP1" DeleteMolecules="0"/>
          <Delete id="RR33_RP2" DeleteMolecules="0"/>
        </ListOfOperations>
      </ReactionRule>
      <ReactionRule id="RR34" name="vPGT" symmetry_factor="1">
        <ListOfReactantPatterns>
          <ReactantPattern id="RR34_RP1">
            <ListOfMolecules>
              <Molecule id="RR34_RP1_M1" name="s3phosphoglycerate" compartment="compartment_2"/>
            </ListOfMolecules>
          </ReactantPattern>
        </ListOfReactantPatterns>
        <ListOfProductPatterns>
          <ProductPattern id="RR34_PP1">
            <ListOfMolecules>
              <Molecule id="RR34_PP1_M1" name="s3phosphoglyceratecytosol" compartment="compartment_1"/>
            </ListOfMolecules>
          </ProductPattern>
        </ListOfProductPatterns>
        <RateLaw id="RR34_RateLaw" type="Ele" totalrate="0">
          <ListOfRateConstants>
            <RateConstant value="r19_k1"/>
          </ListOfRateConstants>
        </RateLaw>
        <Map>
          <MapItem sourceID="RR34_RP1_M1"/>
        </Map>
        <ListOfOperations>
          <Add id="RR34_PP1_M1"/>
          <Delete id="RR34_RP1" DeleteMolecules="0"/>
        </ListOfOperations>
      </ReactionRule>
      <ReactionRule id="RR35" name="_reverse_vPGT" symmetry_factor="1">
        <ListOfReactantPatterns>
          <ReactantPattern id="RR35_RP1">
            <ListOfMolecules>
              <Molecule id="RR35_RP1_M1" name="s3phosphoglyceratecytosol" compartment="compartment_1"/>
            </ListOfMolecules>
          </ReactantPattern>
        </ListOfReactantPatterns>
        <ListOfProductPatterns>
          <ProductPattern id="RR35_PP1">
            <ListOfMolecules>
              <Molecule id="RR35_PP1_M1" name="s3phosphoglycerate" compartment="compartment_2"/>
            </ListOfMolecules>
          </ProductPattern>
        </ListOfProductPatterns>
        <RateLaw id="RR35_RateLaw" type="Ele" totalrate="0">
          <ListOfRateConstants>
            <RateConstant value="r19_k2"/>
          </ListOfRateConstants>
        </RateLaw>
        <Map>
          <MapItem sourceID="RR35_RP1_M1"/>
        </Map>
        <ListOfOperations>
          <Add id="RR35_PP1_M1"/>
          <Delete id="RR35_RP1" DeleteMolecules="0"/>
        </ListOfOperations>
      </ReactionRule>
      <ReactionRule id="RR36" name="vANTI" symmetry_factor="1">
        <ListOfReactantPatterns>
          <ReactantPattern id="RR36_RP1">
            <ListOfMolecules>
              <Molecule id="RR36_RP1_M1" name="glycerol3phosphate" compartment="compartment_2"/>
            </ListOfMolecules>
          </ReactantPattern>
          <ReactantPattern id="RR36_RP2">
            <ListOfMolecules>
              <Molecule id="RR36_RP2_M1" name="dihydroxyacetonephosphatecytosol" compartment="compartment_1"/>
            </ListOfMolecules>
          </ReactantPattern>
        </ListOfReactantPatterns>
        <ListOfProductPatterns>
          <ProductPattern id="RR36_PP1">
            <ListOfMolecules>
              <Molecule id="RR36_PP1_M1" name="glycerol3phosphatecytosol" compartment="compartment_1"/>
            </ListOfMolecules>
          </ProductPattern>
          <ProductPattern id="RR36_PP2">
            <ListOfMolecules>
              <Molecule id="RR36_PP2_M1" name="dihydroxyacetonephosphate" compartment="compartment_2"/>
            </ListOfMolecules>
          </ProductPattern>
        </ListOfProductPatterns>
        <RateLaw id="RR36_RateLaw" type="Ele" totalrate="0">
          <ListOfRateConstants>
            <RateConstant value="r20_k1"/>
          </ListOfRateConstants>
        </RateLaw>
        <Map>
          <MapItem sourceID="RR36_RP1_M1"/>
          <MapItem sourceID="RR36_RP2_M1"/>
        </Map>
        <ListOfOperations>
          <Add id="RR36_PP1_M1"/>
          <Add id="RR36_PP2_M1"/>
          <Delete id="RR36_RP1" DeleteMolecules="0"/>
          <Delete id="RR36_RP2" DeleteMolecules="0"/>
        </ListOfOperations>
      </ReactionRule>
      <ReactionRule id="RR37" name="_reverse_vANTI" symmetry_factor="1">
        <ListOfReactantPatterns>
          <ReactantPattern id="RR37_RP1">
            <ListOfMolecules>
              <Molecule id="RR37_RP1_M1" name="glycerol3phosphatecytosol" compartment="compartment_1"/>
            </ListOfMolecules>
          </ReactantPattern>
          <ReactantPattern id="RR37_RP2">
            <ListOfMolecules>
              <Molecule id="RR37_RP2_M1" name="dihydroxyacetonephosphate" compartment="compartment_2"/>
            </ListOfMolecules>
          </ReactantPattern>
        </ListOfReactantPatterns>
        <ListOfProductPatterns>
          <ProductPattern id="RR37_PP1">
            <ListOfMolecules>
              <Molecule id="RR37_PP1_M1" name="glycerol3phosphate" compartment="compartment_2"/>
            </ListOfMolecules>
          </ProductPattern>
          <ProductPattern id="RR37_PP2">
            <ListOfMolecules>
              <Molecule id="RR37_PP2_M1" name="dihydroxyacetonephosphatecytosol" compartment="compartment_1"/>
            </ListOfMolecules>
          </ProductPattern>
        </ListOfProductPatterns>
        <RateLaw id="RR37_RateLaw" type="Ele" totalrate="0">
          <ListOfRateConstants>
            <RateConstant value="r20_k2"/>
          </ListOfRateConstants>
        </RateLaw>
        <Map>
          <MapItem sourceID="RR37_RP1_M1"/>
          <MapItem sourceID="RR37_RP2_M1"/>
        </Map>
        <ListOfOperations>
          <Add id="RR37_PP1_M1"/>
          <Add id="RR37_PP2_M1"/>
          <Delete id="RR37_RP1" DeleteMolecules="0"/>
          <Delete id="RR37_RP2" DeleteMolecules="0"/>
        </ListOfOperations>
      </ReactionRule>
      <ReactionRule id="RR38" name="vGlyT" symmetry_factor="1">
        <ListOfReactantPatterns>
          <ReactantPattern id="RR38_RP1">
            <ListOfMolecules>
              <Molecule id="RR38_RP1_M1" name="glycerol" compartment="compartment_2"/>
            </ListOfMolecules>
          </ReactantPattern>
        </ListOfReactantPatterns>
        <ListOfProductPatterns>
          <ProductPattern id="RR38_PP1">
            <ListOfMolecules>
              <Molecule id="RR38_PP1_M1" name="glycerolexternal" compartment="compartment_3"/>
            </ListOfMolecules>
          </ProductPattern>
        </ListOfProductPatterns>
        <RateLaw id="RR38_RateLaw" type="Ele" totalrate="0">
          <ListOfRateConstants>
            <RateConstant value="r21_k1"/>
          </ListOfRateConstants>
        </RateLaw>
        <Map>
          <MapItem sourceID="RR38_RP1_M1"/>
        </Map>
        <ListOfOperations>
          <Add id="RR38_PP1_M1"/>
          <Delete id="RR38_RP1" DeleteMolecules="0"/>
        </ListOfOperations>
      </ReactionRule>
      <ReactionRule id="RR39" name="_reverse_vGlyT" symmetry_factor="1">
        <ListOfReactantPatterns>
          <ReactantPattern id="RR39_RP1">
            <ListOfMolecules>
              <Molecule id="RR39_RP1_M1" name="glycerolexternal" compartment="compartment_3"/>
            </ListOfMolecules>
          </ReactantPattern>
        </ListOfReactantPatterns>
        <ListOfProductPatterns>
          <ProductPattern id="RR39_PP1">
            <ListOfMolecules>
              <Molecule id="RR39_PP1_M1" name="glycerol" compartment="compartment_2"/>
            </ListOfMolecules>
          </ProductPattern>
        </ListOfProductPatterns>
        <RateLaw id="RR39_RateLaw" type="Ele" totalrate="0">
          <ListOfRateConstants>
            <RateConstant value="r21_k2"/>
          </ListOfRateConstants>
        </RateLaw>
        <Map>
          <MapItem sourceID="RR39_RP1_M1"/>
        </Map>
        <ListOfOperations>
          <Add id="RR39_PP1_M1"/>
          <Delete id="RR39_RP1" DeleteMolecules="0"/>
        </ListOfOperations>
      </ReactionRule>
    </ListOfReactionRules>
    <ListOfObservables>
      <Observable id="O1" name="pyruvate_compartment_1" type="Species">
        <ListOfPatterns>
          <Pattern id="O1_P1" compartment="compartment_1" matchOnce="1">
            <ListOfMolecules>
              <Molecule id="O1_P1_M1" name="pyruvate"/>
            </ListOfMolecules>
          </Pattern>
        </ListOfPatterns>
      </Observable>
      <Observable id="O2" name="adpc_compartment_1" type="Species">
        <ListOfPatterns>
          <Pattern id="O2_P1" compartment="compartment_1" matchOnce="1">
            <ListOfMolecules>
              <Molecule id="O2_P1_M1" name="adpc"/>
            </ListOfMolecules>
          </Pattern>
        </ListOfPatterns>
      </Observable>
      <Observable id="O3" name="atpc_compartment_1" type="Species">
        <ListOfPatterns>
          <Pattern id="O3_P1" compartment="compartment_1" matchOnce="1">
            <ListOfMolecules>
              <Molecule id="O3_P1_M1" name="atpc"/>
            </ListOfMolecules>
          </Pattern>
        </ListOfPatterns>
      </Observable>
      <Observable id="O4" name="phosphoenolpyruvate_compartment_1" type="Species">
        <ListOfPatterns>
          <Pattern id="O4_P1" compartment="compartment_1" matchOnce="1">
            <ListOfMolecules>
              <Molecule id="O4_P1_M1" name="phosphoenolpyruvate"/>
            </ListOfMolecules>
          </Pattern>
        </ListOfPatterns>
      </Observable>
      <Observable id="O5" name="s2phosphoglycerate_compartment_1" type="Species">
        <ListOfPatterns>
          <Pattern id="O5_P1" compartment="compartment_1" matchOnce="1">
            <ListOfMolecules>
              <Molecule id="O5_P1_M1" name="s2phosphoglycerate"/>
            </ListOfMolecules>
          </Pattern>
        </ListOfPatterns>
      </Observable>
      <Observable id="O6" name="ampc_compartment_1" type="Species">
        <ListOfPatterns>
          <Pattern id="O6_P1" compartment="compartment_1" matchOnce="1">
            <ListOfMolecules>
              <Molecule id="O6_P1_M1" name="ampc"/>
            </ListOfMolecules>
          </Pattern>
        </ListOfPatterns>
      </Observable>
      <Observable id="O7" name="s3phosphoglyceratecytosol_compartment_1" type="Species">
        <ListOfPatterns>
          <Pattern id="O7_P1" compartment="compartment_1" matchOnce="1">
            <ListOfMolecules>
              <Molecule id="O7_P1_M1" name="s3phosphoglyceratecytosol"/>
            </ListOfMolecules>
          </Pattern>
        </ListOfPatterns>
      </Observable>
      <Observable id="O8" name="dihydroxyacetonephosphatecytosol_compartment_1" type="Species">
        <ListOfPatterns>
          <Pattern id="O8_P1" compartment="compartment_1" matchOnce="1">
            <ListOfMolecules>
              <Molecule id="O8_P1_M1" name="dihydroxyacetonephosphatecytosol"/>
            </ListOfMolecules>
          </Pattern>
        </ListOfPatterns>
      </Observable>
      <Observable id="O9" name="glycerol3phosphatecytosol_compartment_1" type="Species">
        <ListOfPatterns>
          <Pattern id="O9_P1" compartment="compartment_1" matchOnce="1">
            <ListOfMolecules>
              <Molecule id="O9_P1_M1" name="glycerol3phosphatecytosol"/>
            </ListOfMolecules>
          </Pattern>
        </ListOfPatterns>
      </Observable>
      <Observable id="O10" name="glucose_compartment_2" type="Species">
        <ListOfPatterns>
          <Pattern id="O10_P1" compartment="compartment_2" matchOnce="1">
            <ListOfMolecules>
              <Molecule id="O10_P1_M1" name="glucose"/>
            </ListOfMolecules>
          </Pattern>
        </ListOfPatterns>
      </Observable>
      <Observable id="O11" name="atpg_compartment_2" type="Species">
        <ListOfPatterns>
          <Pattern id="O11_P1" compartment="compartment_2" matchOnce="1">
            <ListOfMolecules>
              <Molecule id="O11_P1_M1" name="atpg"/>
            </ListOfMolecules>
          </Pattern>
        </ListOfPatterns>
      </Observable>
      <Observable id="O12" name="adpg_compartment_2" type="Species">
        <ListOfPatterns>
          <Pattern id="O12_P1" compartment="compartment_2" matchOnce="1">
            <ListOfMolecules>
              <Molecule id="O12_P1_M1" name="adpg"/>
            </ListOfMolecules>
          </Pattern>
        </ListOfPatterns>
      </Observable>
      <Observable id="O13" name="ampg_compartment_2" type="Species">
        <ListOfPatterns>
          <Pattern id="O13_P1" compartment="compartment_2" matchOnce="1">
            <ListOfMolecules>
              <Molecule id="O13_P1_M1" name="ampg"/>
            </ListOfMolecules>
          </Pattern>
        </ListOfPatterns>
      </Observable>
      <Observable id="O14" name="glucose6phosphate_compartment_2" type="Species">
        <ListOfPatterns>
          <Pattern id="O14_P1" compartment="compartment_2" matchOnce="1">
            <ListOfMolecules>
              <Molecule id="O14_P1_M1" name="glucose6phosphate"/>
            </ListOfMolecules>
          </Pattern>
        </ListOfPatterns>
      </Observable>
      <Observable id="O15" name="fructose6phosphate_compartment_2" type="Species">
        <ListOfPatterns>
          <Pattern id="O15_P1" compartment="compartment_2" matchOnce="1">
            <ListOfMolecules>
              <Molecule id="O15_P1_M1" name="fructose6phosphate"/>
            </ListOfMolecules>
          </Pattern>
        </ListOfPatterns>
      </Observable>
      <Observable id="O16" name="fructose16bisphosphate_compartment_2" type="Species">
        <ListOfPatterns>
          <Pattern id="O16_P1" compartment="compartment_2" matchOnce="1">
            <ListOfMolecules>
              <Molecule id="O16_P1_M1" name="fructose16bisphosphate"/>
            </ListOfMolecules>
          </Pattern>
        </ListOfPatterns>
      </Observable>
      <Observable id="O17" name="dihydroxyacetonephosphate_compartment_2" type="Species">
        <ListOfPatterns>
          <Pattern id="O17_P1" compartment="compartment_2" matchOnce="1">
            <ListOfMolecules>
              <Molecule id="O17_P1_M1" name="dihydroxyacetonephosphate"/>
            </ListOfMolecules>
          </Pattern>
        </ListOfPatterns>
      </Observable>
      <Observable id="O18" name="glyceraldehyde3phosphate_compartment_2" type="Species">
        <ListOfPatterns>
          <Pattern id="O18_P1" compartment="compartment_2" matchOnce="1">
            <ListOfMolecules>
              <Molecule id="O18_P1_M1" name="glyceraldehyde3phosphate"/>
            </ListOfMolecules>
          </Pattern>
        </ListOfPatterns>
      </Observable>
      <Observable id="O19" name="nad_compartment_2" type="Species">
        <ListOfPatterns>
          <Pattern id="O19_P1" compartment="compartment_2" matchOnce="1">
            <ListOfMolecules>
              <Molecule id="O19_P1_M1" name="nad"/>
            </ListOfMolecules>
          </Pattern>
        </ListOfPatterns>
      </Observable>
      <Observable id="O20" name="nadh_compartment_2" type="Species">
        <ListOfPatterns>
          <Pattern id="O20_P1" compartment="compartment_2" matchOnce="1">
            <ListOfMolecules>
              <Molecule id="O20_P1_M1" name="nadh"/>
            </ListOfMolecules>
          </Pattern>
        </ListOfPatterns>
      </Observable>
      <Observable id="O21" name="bisphosphoglycerate_compartment_2" type="Species">
        <ListOfPatterns>
          <Pattern id="O21_P1" compartment="compartment_2" matchOnce="1">
            <ListOfMolecules>
              <Molecule id="O21_P1_M1" name="bisphosphoglycerate"/>
            </ListOfMolecules>
          </Pattern>
        </ListOfPatterns>
      </Observable>
      <Observable id="O22" name="glycerol3phosphate_compartment_2" type="Species">
        <ListOfPatterns>
          <Pattern id="O22_P1" compartment="compartment_2" matchOnce="1">
            <ListOfMolecules>
              <Molecule id="O22_P1_M1" name="glycerol3phosphate"/>
            </ListOfMolecules>
          </Pattern>
        </ListOfPatterns>
      </Observable>
      <Observable id="O23" name="s3phosphoglycerate_compartment_2" type="Species">
        <ListOfPatterns>
          <Pattern id="O23_P1" compartment="compartment_2" matchOnce="1">
            <ListOfMolecules>
              <Molecule id="O23_P1_M1" name="s3phosphoglycerate"/>
            </ListOfMolecules>
          </Pattern>
        </ListOfPatterns>
      </Observable>
      <Observable id="O24" name="glycerol_compartment_2" type="Species">
        <ListOfPatterns>
          <Pattern id="O24_P1" compartment="compartment_2" matchOnce="1">
            <ListOfMolecules>
              <Molecule id="O24_P1_M1" name="glycerol"/>
            </ListOfMolecules>
          </Pattern>
        </ListOfPatterns>
      </Observable>
      <Observable id="O25" name="glucoseexternal_compartment_3" type="Species">
        <ListOfPatterns>
          <Pattern id="O25_P1" compartment="compartment_3" matchOnce="1">
            <ListOfMolecules>
              <Molecule id="O25_P1_M1" name="glucoseexternal"/>
            </ListOfMolecules>
          </Pattern>
        </ListOfPatterns>
      </Observable>
      <Observable id="O26" name="pyruvateexternal_compartment_3" type="Species">
        <ListOfPatterns>
          <Pattern id="O26_P1" compartment="compartment_3" matchOnce="1">
            <ListOfMolecules>
              <Molecule id="O26_P1_M1" name="pyruvateexternal"/>
            </ListOfMolecules>
          </Pattern>
        </ListOfPatterns>
      </Observable>
      <Observable id="O27" name="glycerolexternal_compartment_3" type="Species">
        <ListOfPatterns>
          <Pattern id="O27_P1" compartment="compartment_3" matchOnce="1">
            <ListOfMolecules>
              <Molecule id="O27_P1_M1" name="glycerolexternal"/>
            </ListOfMolecules>
          </Pattern>
        </ListOfPatterns>
      </Observable>
    </ListOfObservables>
    <ListOfFunctions>
      <Function id="fRate0">
        <ListOfReferences>
          <Reference name="glucose_compartment_2" type="Observable"/>
          <Reference name="glucoseexternal_compartment_3" type="Observable"/>
        </ListOfReferences>
        <Expression> 108.9/(((((0.75*glucose_compartment_2)*glucoseexternal_compartment_3)+(1.0*glucose_compartment_2))+(1.0*glucoseexternal_compartment_3))+1.0) </Expression>
      </Function>
      <Function id="fRate0m">
        <ListOfReferences>
          <Reference name="glucose_compartment_2" type="Observable"/>
          <Reference name="glucoseexternal_compartment_3" type="Observable"/>
        </ListOfReferences>
        <Expression> 108.9/(((((0.75*glucose_compartment_2)*glucoseexternal_compartment_3)+(1.0*glucose_compartment_2))+(1.0*glucoseexternal_compartment_3))+1.0) </Expression>
      </Function>
      <Function id="fRate1">
        <ListOfReferences>
          <Reference name="RaHXK" type="Constant"/>
          <Reference name="adpg_compartment_2" type="Observable"/>
          <Reference name="atpg_compartment_2" type="Observable"/>
          <Reference name="glucose6phosphate_compartment_2" type="Observable"/>
          <Reference name="glucose_compartment_2" type="Observable"/>
        </ListOfReferences>
        <Expression> (2916.648*RaHXK)/((((((((0.0116*adpg_compartment_2)*glucose6phosphate_compartment_2)+((1.392*adpg_compartment_2)*(glucose_compartment_2+0.1)))+((1.512*atpg_compartment_2)*glucose_compartment_2))+(0.1512*atpg_compartment_2))+((0.0126*glucose6phosphate_compartment_2)*(atpg_compartment_2+0.116)))+(0.175392*glucose_compartment_2))+0.0175392) </Expression>
      </Function>
      <Function id="fRate2">
        <ListOfReferences>
          <Reference name="fructose6phosphate_compartment_2" type="Observable"/>
          <Reference name="glucose6phosphate_compartment_2" type="Observable"/>
        </ListOfReferences>
        <Expression> 156.6/(((0.4*fructose6phosphate_compartment_2)+(0.12*glucose6phosphate_compartment_2))+0.048) </Expression>
      </Function>
      <Function id="fRate2m">
        <ListOfReferences>
          <Reference name="fructose6phosphate_compartment_2" type="Observable"/>
          <Reference name="glucose6phosphate_compartment_2" type="Observable"/>
        </ListOfReferences>
        <Expression> 522.0/(((0.4*fructose6phosphate_compartment_2)+(0.12*glucose6phosphate_compartment_2))+0.048) </Expression>
      </Function>
      <Function id="fRate3">
        <ListOfReferences>
          <Reference name="RaPFK" type="Constant"/>
          <Reference name="atpg_compartment_2" type="Observable"/>
          <Reference name="fructose16bisphosphate_compartment_2" type="Observable"/>
          <Reference name="fructose6phosphate_compartment_2" type="Observable"/>
        </ListOfReferences>
        <Expression> (288754.48*RaPFK)/(((((((((((0.82*atpg_compartment_2)*(fructose16bisphosphate_compartment_2^2))+(((10.7*atpg_compartment_2)*fructose16bisphosphate_compartment_2)*fructose6phosphate_compartment_2))+((21.73*atpg_compartment_2)*fructose16bisphosphate_compartment_2))+((169.06*atpg_compartment_2)*fructose6phosphate_compartment_2))+(138.6292*atpg_compartment_2))+(0.02132*(fructose16bisphosphate_compartment_2^2)))+((0.2782*fructose16bisphosphate_compartment_2)*fructose6phosphate_compartment_2))+(0.56498*fructose16bisphosphate_compartment_2))+(4.39556*fructose6phosphate_compartment_2))+3.6043592) </Expression>
      </Function>
      <Function id="fRate4">
        <ListOfReferences>
          <Reference name="adpg_compartment_2" type="Observable"/>
          <Reference name="ampg_compartment_2" type="Observable"/>
          <Reference name="atpg_compartment_2" type="Observable"/>
          <Reference name="dihydroxyacetonephosphate_compartment_2" type="Observable"/>
          <Reference name="fructose16bisphosphate_compartment_2" type="Observable"/>
          <Reference name="glyceraldehyde3phosphate_compartment_2" type="Observable"/>
        </ListOfReferences>
        <Expression> 4.5061968/(((((((((((((0.000973509933774835*adpg_compartment_2)*glyceraldehyde3phosphate_compartment_2)+(4.7960940397351e-5*adpg_compartment_2))+((0.000402739726027397*ampg_compartment_2)*glyceraldehyde3phosphate_compartment_2))+(1.98413753424657e-5*ampg_compartment_2))+((0.00216176470588236*atpg_compartment_2)*glyceraldehyde3phosphate_compartment_2))+(0.0001065015*atpg_compartment_2))+((0.098*dihydroxyacetonephosphate_compartment_2)*glyceraldehyde3phosphate_compartment_2))+(0.006566*dihydroxyacetonephosphate_compartment_2))+((0.08211*fructose16bisphosphate_compartment_2)*glyceraldehyde3phosphate_compartment_2))+(0.00804678*fructose16bisphosphate_compartment_2))+(0.00147*glyceraldehyde3phosphate_compartment_2))+7.242102e-5) </Expression>
      </Function>
      <Function id="fRate4m">
        <ListOfReferences>
          <Reference name="adpg_compartment_2" type="Observable"/>
          <Reference name="ampg_compartment_2" type="Observable"/>
          <Reference name="atpg_compartment_2" type="Observable"/>
          <Reference name="dihydroxyacetonephosphate_compartment_2" type="Observable"/>
          <Reference name="fructose16bisphosphate_compartment_2" type="Observable"/>
          <Reference name="glyceraldehyde3phosphate_compartment_2" type="Observable"/>
        </ListOfReferences>
        <Expression> 65.3072/(((((((((((((0.000973509933774835*adpg_compartment_2)*glyceraldehyde3phosphate_compartment_2)+(4.7960940397351e-5*adpg_compartment_2))+((0.000402739726027397*ampg_compartment_2)*glyceraldehyde3phosphate_compartment_2))+(1.98413753424657e-5*ampg_compartment_2))+((0.00216176470588236*atpg_compartment_2)*glyceraldehyde3phosphate_compartment_2))+(0.0001065015*atpg_compartment_2))+((0.098*dihydroxyacetonephosphate_compartment_2)*glyceraldehyde3phosphate_compartment_2))+(0.006566*dihydroxyacetonephosphate_compartment_2))+((0.08211*fructose16bisphosphate_compartment_2)*glyceraldehyde3phosphate_compartment_2))+(0.00804678*fructose16bisphosphate_compartment_2))+(0.00147*glyceraldehyde3phosphate_compartment_2))+7.242102e-5) </Expression>
      </Function>
      <Function id="fRate5">
        <ListOfReferences>
          <Reference name="dihydroxyacetonephosphate_compartment_2" type="Observable"/>
          <Reference name="glyceraldehyde3phosphate_compartment_2" type="Observable"/>
        </ListOfReferences>
        <Expression> 249.825/(((0.25*dihydroxyacetonephosphate_compartment_2)+(1.2*glyceraldehyde3phosphate_compartment_2))+0.3) </Expression>
      </Function>
      <Function id="fRate5m">
        <ListOfReferences>
          <Reference name="dihydroxyacetonephosphate_compartment_2" type="Observable"/>
          <Reference name="glyceraldehyde3phosphate_compartment_2" type="Observable"/>
        </ListOfReferences>
        <Expression> 6835.212/(((0.25*dihydroxyacetonephosphate_compartment_2)+(1.2*glyceraldehyde3phosphate_compartment_2))+0.3) </Expression>
      </Function>
      <Function id="fRate6">
        <ListOfReferences>
          <Reference name="bisphosphoglycerate_compartment_2" type="Observable"/>
          <Reference name="glyceraldehyde3phosphate_compartment_2" type="Observable"/>
          <Reference name="nad_compartment_2" type="Observable"/>
          <Reference name="nadh_compartment_2" type="Observable"/>
        </ListOfReferences>
        <Expression> 1.4418/((((((((0.0675*bisphosphoglycerate_compartment_2)*nadh_compartment_2)+((0.003*bisphosphoglycerate_compartment_2)*(nad_compartment_2+0.45)))+((0.002*glyceraldehyde3phosphate_compartment_2)*nad_compartment_2))+(0.0009*glyceraldehyde3phosphate_compartment_2))+(0.0003*nad_compartment_2))+((0.045*nadh_compartment_2)*(glyceraldehyde3phosphate_compartment_2+0.15)))+0.000135) </Expression>
      </Function>
      <Function id="fRate6m">
        <ListOfReferences>
          <Reference name="bisphosphoglycerate_compartment_2" type="Observable"/>
          <Reference name="glyceraldehyde3phosphate_compartment_2" type="Observable"/>
          <Reference name="nad_compartment_2" type="Observable"/>
          <Reference name="nadh_compartment_2" type="Observable"/>
        </ListOfReferences>
        <Expression> 32.6027025/((((((((0.0675*bisphosphoglycerate_compartment_2)*nadh_compartment_2)+(0.00135*bisphosphoglycerate_compartment_2))+((0.002*glyceraldehyde3phosphate_compartment_2)*nad_compartment_2))+((0.045*glyceraldehyde3phosphate_compartment_2)*(nadh_compartment_2+0.02)))+((0.003*nad_compartment_2)*(bisphosphoglycerate_compartment_2+0.1)))+(0.00675*nadh_compartment_2))+0.000135) </Expression>
      </Function>
      <Function id="fRate7">
        <ListOfReferences>
          <Reference name="dihydroxyacetonephosphate_compartment_2" type="Observable"/>
          <Reference name="glycerol3phosphate_compartment_2" type="Observable"/>
          <Reference name="nad_compartment_2" type="Observable"/>
          <Reference name="nadh_compartment_2" type="Observable"/>
        </ListOfReferences>
        <Expression> 372.0/((((((((0.8*dihydroxyacetonephosphate_compartment_2)*nadh_compartment_2)+(0.008*dihydroxyacetonephosphate_compartment_2))+((0.001*glycerol3phosphate_compartment_2)*nad_compartment_2))+((0.04*glycerol3phosphate_compartment_2)*(nadh_compartment_2+0.01)))+((0.02*nad_compartment_2)*(dihydroxyacetonephosphate_compartment_2+0.1)))+(0.08*nadh_compartment_2))+0.0008) </Expression>
      </Function>
      <Function id="fRate7m">
        <ListOfReferences>
          <Reference name="dihydroxyacetonephosphate_compartment_2" type="Observable"/>
          <Reference name="glycerol3phosphate_compartment_2" type="Observable"/>
          <Reference name="nad_compartment_2" type="Observable"/>
          <Reference name="nadh_compartment_2" type="Observable"/>
        </ListOfReferences>
        <Expression> 0.1302/((((((((0.8*dihydroxyacetonephosphate_compartment_2)*nadh_compartment_2)+((0.02*dihydroxyacetonephosphate_compartment_2)*(nad_compartment_2+0.4)))+((0.001*glycerol3phosphate_compartment_2)*nad_compartment_2))+(0.0004*glycerol3phosphate_compartment_2))+(0.002*nad_compartment_2))+((0.04*nadh_compartment_2)*(glycerol3phosphate_compartment_2+2.0)))+0.0008) </Expression>
      </Function>
      <Function id="fRate8">
        <ListOfReferences>
          <Reference name="glycerol3phosphatecytosol_compartment_1" type="Observable"/>
        </ListOfReferences>
        <Expression> 368.0/(glycerol3phosphatecytosol_compartment_1+1.7) </Expression>
      </Function>
      <Function id="fRate9">
        <ListOfReferences>
          <Reference name="pyruvate_compartment_1" type="Observable"/>
        </ListOfReferences>
        <Expression> 200.0/(pyruvate_compartment_1+1.96) </Expression>
      </Function>
      <Function id="fRate10">
        <ListOfReferences>
          <Reference name="adpg_compartment_2" type="Observable"/>
          <Reference name="atpg_compartment_2" type="Observable"/>
          <Reference name="bisphosphoglycerate_compartment_2" type="Observable"/>
          <Reference name="s3phosphoglycerate_compartment_2" type="Observable"/>
        </ListOfReferences>
        <Expression> 1344.5676/((((((((0.4698*adpg_compartment_2)*bisphosphoglycerate_compartment_2)+(0.0014094*adpg_compartment_2))+((0.0003*atpg_compartment_2)*s3phosphoglycerate_compartment_2))+((0.162*atpg_compartment_2)*(bisphosphoglycerate_compartment_2+0.003)))+(0.04698*bisphosphoglycerate_compartment_2))+((0.00087*s3phosphoglycerate_compartment_2)*(adpg_compartment_2+0.1)))+0.00014094) </Expression>
      </Function>
      <Function id="fRate10m">
        <ListOfReferences>
          <Reference name="adpg_compartment_2" type="Observable"/>
          <Reference name="atpg_compartment_2" type="Observable"/>
          <Reference name="bisphosphoglycerate_compartment_2" type="Observable"/>
          <Reference name="s3phosphoglycerate_compartment_2" type="Observable"/>
        </ListOfReferences>
        <Expression> 0.403542/((((((((0.4698*adpg_compartment_2)*bisphosphoglycerate_compartment_2)+((0.00087*adpg_compartment_2)*(s3phosphoglycerate_compartment_2+1.62)))+((0.0003*atpg_compartment_2)*s3phosphoglycerate_compartment_2))+(0.000486*atpg_compartment_2))+((0.162*bisphosphoglycerate_compartment_2)*(atpg_compartment_2+0.29)))+(8.7e-5*s3phosphoglycerate_compartment_2))+0.00014094) </Expression>
      </Function>
      <Function id="fRate11">
        <ListOfReferences>
          <Reference name="RaPYK" type="Constant"/>
          <Reference name="adpc_compartment_1" type="Observable"/>
          <Reference name="atpc_compartment_1" type="Observable"/>
          <Reference name="phosphoenolpyruvate_compartment_1" type="Observable"/>
        </ListOfReferences>
        <Expression> (((1020.0*RaPYK)*adpc_compartment_1)*((phosphoenolpyruvate_compartment_1/(((0.53125*adpc_compartment_1)+(0.596491228070176*atpc_compartment_1))+0.34))^2.5))/(((1.0*adpc_compartment_1)+0.114)*(((phosphoenolpyruvate_compartment_1/(((0.53125*adpc_compartment_1)+(0.596491228070176*atpc_compartment_1))+0.34))^2.5)+1)) </Expression>
      </Function>
      <Function id="fRate12">
        <ListOfReferences>
          <Reference name="adpc_compartment_1" type="Observable"/>
        </ListOfReferences>
        <Expression> 50.0/adpc_compartment_1 </Expression>
      </Function>
      <Function id="fRate13">
        <ListOfReferences>
          <Reference name="adpg_compartment_2" type="Observable"/>
          <Reference name="atpg_compartment_2" type="Observable"/>
          <Reference name="glycerol3phosphate_compartment_2" type="Observable"/>
          <Reference name="glycerol_compartment_2" type="Observable"/>
        </ListOfReferences>
        <Expression> 21.12/((((((((0.1056*adpg_compartment_2)*glycerol3phosphate_compartment_2)+(0.404448*adpg_compartment_2))+((2.1448*atpg_compartment_2)*glycerol_compartment_2))+((0.2464*atpg_compartment_2)*(glycerol3phosphate_compartment_2+3.83)))+(0.059136*glycerol3phosphate_compartment_2))+((0.9192*glycerol_compartment_2)*(adpg_compartment_2+0.56)))+0.22649088) </Expression>
      </Function>
      <Function id="fRate13m">
        <ListOfReferences>
          <Reference name="adpg_compartment_2" type="Observable"/>
          <Reference name="atpg_compartment_2" type="Observable"/>
          <Reference name="glycerol3phosphate_compartment_2" type="Observable"/>
          <Reference name="glycerol_compartment_2" type="Observable"/>
        </ListOfReferences>
        <Expression> 26106.5056/((((((((0.1056*adpg_compartment_2)*glycerol3phosphate_compartment_2)+((0.9192*adpg_compartment_2)*(glycerol_compartment_2+0.44)))+((2.1448*atpg_compartment_2)*glycerol_compartment_2))+(0.943712*atpg_compartment_2))+((0.2464*glycerol3phosphate_compartment_2)*(atpg_compartment_2+0.24)))+(0.514752*glycerol_compartment_2))+0.22649088) </Expression>
      </Function>
      <Function id="fRate14">
        <ListOfReferences>
          <Reference name="RaPGAM" type="Constant"/>
          <Reference name="s2phosphoglycerate_compartment_1" type="Observable"/>
          <Reference name="s3phosphoglyceratecytosol_compartment_1" type="Observable"/>
        </ListOfReferences>
        <Expression> (24.75*RaPGAM)/(((0.27*s2phosphoglycerate_compartment_1)+(0.11*s3phosphoglyceratecytosol_compartment_1))+0.0297) </Expression>
      </Function>
      <Function id="fRate14m">
        <ListOfReferences>
          <Reference name="RaPGAM" type="Constant"/>
          <Reference name="s2phosphoglycerate_compartment_1" type="Observable"/>
          <Reference name="s3phosphoglyceratecytosol_compartment_1" type="Observable"/>
        </ListOfReferences>
        <Expression> (133.65*RaPGAM)/(((0.27*s2phosphoglycerate_compartment_1)+(0.11*s3phosphoglyceratecytosol_compartment_1))+0.0297) </Expression>
      </Function>
      <Function id="fRate15">
        <ListOfReferences>
          <Reference name="RaENO" type="Constant"/>
          <Reference name="phosphoenolpyruvate_compartment_1" type="Observable"/>
          <Reference name="s2phosphoglycerate_compartment_1" type="Observable"/>
        </ListOfReferences>
        <Expression> (143.52*RaENO)/(((0.054*phosphoenolpyruvate_compartment_1)+(0.24*s2phosphoglycerate_compartment_1))+0.01296) </Expression>
      </Function>
      <Function id="fRate15m">
        <ListOfReferences>
          <Reference name="RaENO" type="Constant"/>
          <Reference name="phosphoenolpyruvate_compartment_1" type="Observable"/>
          <Reference name="s2phosphoglycerate_compartment_1" type="Observable"/>
        </ListOfReferences>
        <Expression> (21.31272*RaENO)/(((0.054*phosphoenolpyruvate_compartment_1)+(0.24*s2phosphoglycerate_compartment_1))+0.01296) </Expression>
      </Function>
      <Function id="fRate16m">
        <ListOfReferences>
        </ListOfReferences>
        <Expression> 442000.0 </Expression>
      </Function>
      <Function id="fRate17m">
        <ListOfReferences>
        </ListOfReferences>
        <Expression> 442000.0 </Expression>
      </Function>
      <Function id="_rateLaw1">
        <ListOfReferences>
          <Reference name="fRate11" type="Function"/>
        </ListOfReferences>
        <Expression> -1*fRate11() </Expression>
      </Function>
      <Function id="_rateLaw2">
        <ListOfReferences>
          <Reference name="fRate11" type="Function"/>
        </ListOfReferences>
        <Expression> -1*fRate11() </Expression>
      </Function>
    </ListOfFunctions>
  </model>
</sbml>
